{
"meta":{"test_sets":[],"test_metrics":[],"learn_metrics":[{"best_value":"Min","name":"RMSE"}],"launch_mode":"Train","parameters":"","iteration_count":1000,"learn_sets":["learn"],"name":"experiment"},
"iterations":[
{"learn":[14.61268541],"iteration":0,"passed_time":0.3660988368,"remaining_time":365.732738},
{"learn":[14.23196558],"iteration":1,"passed_time":0.3675149312,"remaining_time":183.3899507},
{"learn":[13.86674177],"iteration":2,"passed_time":0.3688701428,"remaining_time":122.5878441},
{"learn":[13.49946468],"iteration":3,"passed_time":0.3697925457,"remaining_time":92.07834387},
{"learn":[13.16661202],"iteration":4,"passed_time":0.3707516885,"remaining_time":73.77958601},
{"learn":[12.85632158],"iteration":5,"passed_time":0.3716875034,"remaining_time":61.57622973},
{"learn":[12.56784336],"iteration":6,"passed_time":0.372643867,"remaining_time":52.86219428},
{"learn":[12.31617801],"iteration":7,"passed_time":0.3736075445,"remaining_time":46.32733552},
{"learn":[12.01509946],"iteration":8,"passed_time":0.3745224227,"remaining_time":41.2390801},
{"learn":[11.71512571],"iteration":9,"passed_time":0.3754418602,"remaining_time":37.16874416},
{"learn":[11.43264457],"iteration":10,"passed_time":0.3765053518,"remaining_time":33.8512539},
{"learn":[11.17973129],"iteration":11,"passed_time":0.379077809,"remaining_time":31.21073961},
{"learn":[10.93746433],"iteration":12,"passed_time":0.3803630002,"remaining_time":28.87832932},
{"learn":[10.69387075],"iteration":13,"passed_time":0.3816284164,"remaining_time":26.87754418},
{"learn":[10.4615922],"iteration":14,"passed_time":0.3828577217,"remaining_time":25.14099039},
{"learn":[10.2299235],"iteration":15,"passed_time":0.3839260786,"remaining_time":23.61145383},
{"learn":[10.01419731],"iteration":16,"passed_time":0.3848840102,"remaining_time":22.25535188},
{"learn":[9.795856918],"iteration":17,"passed_time":0.3858166724,"remaining_time":21.0484429},
{"learn":[9.60040151],"iteration":18,"passed_time":0.386765503,"remaining_time":19.9693136},
{"learn":[9.418664989],"iteration":19,"passed_time":0.3877215343,"remaining_time":18.99835518},
{"learn":[9.249278645],"iteration":20,"passed_time":0.3887172764,"remaining_time":18.12162922},
{"learn":[9.090113396],"iteration":21,"passed_time":0.3896826944,"remaining_time":17.32316705},
{"learn":[8.909548708],"iteration":22,"passed_time":0.391241959,"remaining_time":16.619278},
{"learn":[8.740140208],"iteration":23,"passed_time":0.3932882695,"remaining_time":15.99372296},
{"learn":[8.59377682],"iteration":24,"passed_time":0.3944774938,"remaining_time":15.38462226},
{"learn":[8.453885414],"iteration":25,"passed_time":0.3957729793,"remaining_time":14.82626469},
{"learn":[8.317732234],"iteration":26,"passed_time":0.3970040617,"remaining_time":14.30685007},
{"learn":[8.180896085],"iteration":27,"passed_time":0.3980123315,"remaining_time":13.81671379},
{"learn":[8.053220863],"iteration":28,"passed_time":0.3989768476,"remaining_time":13.35884548},
{"learn":[7.924234474],"iteration":29,"passed_time":0.3999409015,"remaining_time":12.93142248},
{"learn":[7.818879511],"iteration":30,"passed_time":0.4008994252,"remaining_time":12.5313401},
{"learn":[7.719346395],"iteration":31,"passed_time":0.4018409952,"remaining_time":12.1556901},
{"learn":[7.624163594],"iteration":32,"passed_time":0.4027814043,"remaining_time":11.8027157},
{"learn":[7.524952543],"iteration":33,"passed_time":0.4037295663,"remaining_time":11.47066944},
{"learn":[7.424464745],"iteration":34,"passed_time":0.4056579289,"remaining_time":11.18456861},
{"learn":[7.327482321],"iteration":35,"passed_time":0.4074014053,"remaining_time":10.9093043},
{"learn":[7.238666841],"iteration":36,"passed_time":0.4084847706,"remaining_time":10.63164417},
{"learn":[7.158842395],"iteration":37,"passed_time":0.4095041946,"remaining_time":10.36692198},
{"learn":[7.074348246],"iteration":38,"passed_time":0.4105324739,"remaining_time":10.11594122},
{"learn":[6.992269093],"iteration":39,"passed_time":0.4118978611,"remaining_time":9.885548668},
{"learn":[6.925219745],"iteration":40,"passed_time":0.4130795767,"remaining_time":9.66203205},
{"learn":[6.86013671],"iteration":41,"passed_time":0.4140767553,"remaining_time":9.444893608},
{"learn":[6.786739622],"iteration":42,"passed_time":0.415021996,"remaining_time":9.236652329},
{"learn":[6.73057926],"iteration":43,"passed_time":0.41596952,"remaining_time":9.037883208},
{"learn":[6.666356486],"iteration":44,"passed_time":0.4169232088,"remaining_time":8.848036987},
{"learn":[6.606182832],"iteration":45,"passed_time":0.4178627386,"remaining_time":8.66610984},
{"learn":[6.547854615],"iteration":46,"passed_time":0.4194231936,"remaining_time":8.504474543},
{"learn":[6.49240675],"iteration":47,"passed_time":0.4212977243,"remaining_time":8.355738199},
{"learn":[6.431317261],"iteration":48,"passed_time":0.4224530599,"remaining_time":8.199037959},
{"learn":[6.377586395],"iteration":49,"passed_time":0.4235068389,"remaining_time":8.046629939},
{"learn":[6.327558015],"iteration":50,"passed_time":0.424551091,"remaining_time":7.899980104},
{"learn":[6.282040317],"iteration":51,"passed_time":0.4255361153,"remaining_time":7.757850718},
{"learn":[6.237655841],"iteration":52,"passed_time":0.4266050897,"remaining_time":7.622547546},
{"learn":[6.192792003],"iteration":53,"passed_time":0.4281848289,"remaining_time":7.501163854},
{"learn":[6.150579347],"iteration":54,"passed_time":0.4293419132,"remaining_time":7.376874691},
{"learn":[6.115693845],"iteration":55,"passed_time":0.4304612438,"remaining_time":7.25634668},
{"learn":[6.078780782],"iteration":56,"passed_time":0.4314869137,"remaining_time":7.13845894},
{"learn":[6.045146957],"iteration":57,"passed_time":0.4327011043,"remaining_time":7.027662763},
{"learn":[6.008080327],"iteration":58,"passed_time":0.4350841389,"remaining_time":6.9392233},
{"learn":[5.977575734],"iteration":59,"passed_time":0.436141609,"remaining_time":6.832885208},
{"learn":[5.948036502],"iteration":60,"passed_time":0.4371639005,"remaining_time":6.729457419},
{"learn":[5.914888282],"iteration":61,"passed_time":0.4381025109,"remaining_time":6.62806702},
{"learn":[5.884957796],"iteration":62,"passed_time":0.4390478457,"remaining_time":6.529965578},
{"learn":[5.849539885],"iteration":63,"passed_time":0.440007163,"remaining_time":6.435104759},
{"learn":[5.821387627],"iteration":64,"passed_time":0.4409623832,"remaining_time":6.343074282},
{"learn":[5.797012279],"iteration":65,"passed_time":0.4419135597,"remaining_time":6.253746435},
{"learn":[5.768685095],"iteration":66,"passed_time":0.4428398256,"remaining_time":6.16670981},
{"learn":[5.755484587],"iteration":67,"passed_time":0.443339109,"remaining_time":6.07635367},
{"learn":[5.731887055],"iteration":68,"passed_time":0.4442781191,"remaining_time":5.994535201},
{"learn":[5.707148487],"iteration":69,"passed_time":0.4451917973,"remaining_time":5.914691022},
{"learn":[5.685365039],"iteration":70,"passed_time":0.4461269993,"remaining_time":5.837351865},
{"learn":[5.663541834],"iteration":71,"passed_time":0.4472458606,"remaining_time":5.764502203},
{"learn":[5.638108797],"iteration":72,"passed_time":0.4498607279,"remaining_time":5.712614997},
{"learn":[5.619204893],"iteration":73,"passed_time":0.4507902407,"remaining_time":5.640969768},
{"learn":[5.598472793],"iteration":74,"passed_time":0.451707807,"remaining_time":5.571062952},
{"learn":[5.577007075],"iteration":75,"passed_time":0.4525944462,"remaining_time":5.502595635},
{"learn":[5.562637084],"iteration":76,"passed_time":0.4537026788,"remaining_time":5.438539903},
{"learn":[5.54729991],"iteration":77,"passed_time":0.4548308746,"remaining_time":5.376334184},
{"learn":[5.530737623],"iteration":78,"passed_time":0.4557906624,"remaining_time":5.313711393},
{"learn":[5.513704873],"iteration":79,"passed_time":0.4566746893,"remaining_time":5.251758927},
{"learn":[5.501575529],"iteration":80,"passed_time":0.4575947663,"remaining_time":5.191723336},
{"learn":[5.484080734],"iteration":81,"passed_time":0.4584736461,"remaining_time":5.132668379},
{"learn":[5.472178894],"iteration":82,"passed_time":0.4594140144,"remaining_time":5.075694593},
{"learn":[5.458923342],"iteration":83,"passed_time":0.460304525,"remaining_time":5.019511249},
{"learn":[5.451382371],"iteration":84,"passed_time":0.4609120319,"remaining_time":4.961582461},
{"learn":[5.441410748],"iteration":85,"passed_time":0.4618562084,"remaining_time":4.908564819},
{"learn":[5.434047468],"iteration":86,"passed_time":0.463271764,"remaining_time":4.86169104},
{"learn":[5.422107497],"iteration":87,"passed_time":0.4643518716,"remaining_time":4.812373943},
{"learn":[5.40731265],"iteration":88,"passed_time":0.465277533,"remaining_time":4.762559916},
{"learn":[5.396360181],"iteration":89,"passed_time":0.4661696491,"remaining_time":4.713493119},
{"learn":[5.383793239],"iteration":90,"passed_time":0.4671400173,"remaining_time":4.666266766},
{"learn":[5.369605034],"iteration":91,"passed_time":0.4680706759,"remaining_time":4.619654062},
{"learn":[5.357467333],"iteration":92,"passed_time":0.469003214,"remaining_time":4.574042098},
{"learn":[5.341109968],"iteration":93,"passed_time":0.4699368404,"remaining_time":4.529391249},
{"learn":[5.330529276],"iteration":94,"passed_time":0.4708679471,"remaining_time":4.485636759},
{"learn":[5.319862075],"iteration":95,"passed_time":0.4717556647,"remaining_time":4.442365842},
{"learn":[5.313052243],"iteration":96,"passed_time":0.4726391994,"remaining_time":4.399929867},
{"learn":[5.299677207],"iteration":97,"passed_time":0.4735256146,"remaining_time":4.358368412},
{"learn":[5.287546698],"iteration":98,"passed_time":0.4744623739,"remaining_time":4.318086857},
{"learn":[5.279803754],"iteration":99,"passed_time":0.4753663099,"remaining_time":4.278296789},
{"learn":[5.272254612],"iteration":100,"passed_time":0.4762925708,"remaining_time":4.239475457},
{"learn":[5.268813888],"iteration":101,"passed_time":0.4770321775,"remaining_time":4.199753877},
{"learn":[5.258113767],"iteration":102,"passed_time":0.4787112345,"remaining_time":4.168970654},
{"learn":[5.251018576],"iteration":103,"passed_time":0.479597514,"remaining_time":4.131917043},
{"learn":[5.24171237],"iteration":104,"passed_time":0.4805583277,"remaining_time":4.09618765},
{"learn":[5.233984943],"iteration":105,"passed_time":0.4814823261,"remaining_time":4.060803769},
{"learn":[5.226240449],"iteration":106,"passed_time":0.4823868475,"remaining_time":4.025901447},
{"learn":[5.220541644],"iteration":107,"passed_time":0.483286584,"remaining_time":3.991589194},
{"learn":[5.211712096],"iteration":108,"passed_time":0.4841983828,"remaining_time":3.957988615},
{"learn":[5.203388597],"iteration":109,"passed_time":0.4850962598,"remaining_time":3.924869738},
{"learn":[5.196026544],"iteration":110,"passed_time":0.4859954675,"remaining_time":3.892342078},
{"learn":[5.188716772],"iteration":111,"passed_time":0.4869059414,"remaining_time":3.860468535},
{"learn":[5.182163132],"iteration":112,"passed_time":0.48778645,"remaining_time":3.828907797},
{"learn":[5.17764747],"iteration":113,"passed_time":0.4886655512,"remaining_time":3.797874372},
{"learn":[5.170548056],"iteration":114,"passed_time":0.4895837479,"remaining_time":3.767666234},
{"learn":[5.165901827],"iteration":115,"passed_time":0.4902973565,"remaining_time":3.736403993},
{"learn":[5.160333668],"iteration":116,"passed_time":0.4912407652,"remaining_time":3.707398253},
{"learn":[5.148953243],"iteration":117,"passed_time":0.492856701,"remaining_time":3.683895002},
{"learn":[5.144729126],"iteration":118,"passed_time":0.4936756594,"remaining_time":3.654859293},
{"learn":[5.139939946],"iteration":119,"passed_time":0.4946350991,"remaining_time":3.62732406},
{"learn":[5.132898872],"iteration":120,"passed_time":0.4956220017,"remaining_time":3.600427599},
{"learn":[5.129073077],"iteration":121,"passed_time":0.4965459284,"remaining_time":3.573502665},
{"learn":[5.127123916],"iteration":122,"passed_time":0.4970260313,"remaining_time":3.543836012},
{"learn":[5.121282057],"iteration":123,"passed_time":0.4979138913,"remaining_time":3.517520716},
{"learn":[5.114489821],"iteration":124,"passed_time":0.4988016947,"remaining_time":3.491611863},
{"learn":[5.107777291],"iteration":125,"passed_time":0.4996908455,"remaining_time":3.466109515},
{"learn":[5.103518754],"iteration":126,"passed_time":0.5006090013,"remaining_time":3.441194159},
{"learn":[5.101133351],"iteration":127,"passed_time":0.5012199841,"remaining_time":3.414561142},
{"learn":[5.096462705],"iteration":128,"passed_time":0.5021653405,"remaining_time":3.390589237},
{"learn":[5.08562082],"iteration":129,"passed_time":0.5030618702,"remaining_time":3.366644824},
{"learn":[5.080483682],"iteration":130,"passed_time":0.5039554636,"remaining_time":3.343032808},
{"learn":[5.07437499],"iteration":131,"passed_time":0.504850725,"remaining_time":3.319775979},
{"learn":[5.070683732],"iteration":132,"passed_time":0.505785504,"remaining_time":3.297113022},
{"learn":[5.06432037],"iteration":133,"passed_time":0.5071803144,"remaining_time":3.277747405},
{"learn":[5.057436484],"iteration":134,"passed_time":0.5084435109,"remaining_time":3.257804718},
{"learn":[5.053254656],"iteration":135,"passed_time":0.5094706252,"remaining_time":3.236636913},
{"learn":[5.04801663],"iteration":136,"passed_time":0.5104781489,"remaining_time":3.215639726},
{"learn":[5.045680836],"iteration":137,"passed_time":0.5113006597,"remaining_time":3.193776585},
{"learn":[5.041857933],"iteration":138,"passed_time":0.5124020455,"remaining_time":3.173943606},
{"learn":[5.035264888],"iteration":139,"passed_time":0.5135380221,"remaining_time":3.154590707},
{"learn":[5.028771948],"iteration":140,"passed_time":0.5147310845,"remaining_time":3.135843983},
{"learn":[5.024912247],"iteration":141,"passed_time":0.5157649431,"remaining_time":3.116382544},
{"learn":[5.02239068],"iteration":142,"passed_time":0.516799824,"remaining_time":3.097184959},
{"learn":[5.017110572],"iteration":143,"passed_time":0.517852988,"remaining_time":3.078348318},
{"learn":[5.010707886],"iteration":144,"passed_time":0.5188776428,"remaining_time":3.059588859},
{"learn":[5.004389868],"iteration":145,"passed_time":0.5198167795,"remaining_time":3.040572121},
{"learn":[4.997628683],"iteration":146,"passed_time":0.520702611,"remaining_time":3.021492021},
{"learn":[4.991497851],"iteration":147,"passed_time":0.5224436557,"remaining_time":3.007581045},
{"learn":[4.988345253],"iteration":148,"passed_time":0.5235268941,"remaining_time":2.990076422},
{"learn":[4.98460423],"iteration":149,"passed_time":0.5244201602,"remaining_time":2.971714241},
{"learn":[4.982441783],"iteration":150,"passed_time":0.525323266,"remaining_time":2.953638761},
{"learn":[4.977461771],"iteration":151,"passed_time":0.5262206251,"remaining_time":2.935757172},
{"learn":[4.973601586],"iteration":152,"passed_time":0.5271291578,"remaining_time":2.918159455},
{"learn":[4.968328804],"iteration":153,"passed_time":0.5280444387,"remaining_time":2.900815553},
{"learn":[4.9640736],"iteration":154,"passed_time":0.5290219913,"remaining_time":2.884023114},
{"learn":[4.960865882],"iteration":155,"passed_time":0.5299005896,"remaining_time":2.866898061},
{"learn":[4.957014156],"iteration":156,"passed_time":0.5307818068,"remaining_time":2.849994033},
{"learn":[4.952244852],"iteration":157,"passed_time":0.5317002533,"remaining_time":2.833491223},
{"learn":[4.949695675],"iteration":158,"passed_time":0.5325937909,"remaining_time":2.817052693},
{"learn":[4.946584698],"iteration":159,"passed_time":0.533474745,"remaining_time":2.800742411},
{"learn":[4.940192834],"iteration":160,"passed_time":0.5344205536,"remaining_time":2.784961767},
{"learn":[4.936727994],"iteration":161,"passed_time":0.535316004,"remaining_time":2.769103774},
{"learn":[4.932342063],"iteration":162,"passed_time":0.5370634572,"remaining_time":2.757804378},
{"learn":[4.925830838],"iteration":163,"passed_time":0.5387769183,"remaining_time":2.746448193},
{"learn":[4.922571773],"iteration":164,"passed_time":0.5402171425,"remaining_time":2.733826146},
{"learn":[4.918395814],"iteration":165,"passed_time":0.5417303425,"remaining_time":2.721705456},
{"learn":[4.911142452],"iteration":166,"passed_time":0.5430380593,"remaining_time":2.708686847},
{"learn":[4.908276131],"iteration":167,"passed_time":0.5444572935,"remaining_time":2.69635993},
{"learn":[4.904584645],"iteration":168,"passed_time":0.5455563544,"remaining_time":2.682587754},
{"learn":[4.89795517],"iteration":169,"passed_time":0.5467319992,"remaining_time":2.669338584},
{"learn":[4.895556491],"iteration":170,"passed_time":0.5483694638,"remaining_time":2.658469506},
{"learn":[4.890591233],"iteration":171,"passed_time":0.5498053316,"remaining_time":2.646737294},
{"learn":[4.884629277],"iteration":172,"passed_time":0.551402495,"remaining_time":2.635895164},
{"learn":[4.880550786],"iteration":173,"passed_time":0.5530418853,"remaining_time":2.625359754},
{"learn":[4.876384842],"iteration":174,"passed_time":0.5544649405,"remaining_time":2.613906148},
{"learn":[4.872638238],"iteration":175,"passed_time":0.5558174773,"remaining_time":2.602236371},
{"learn":[4.869137118],"iteration":176,"passed_time":0.5570954891,"remaining_time":2.590336653},
{"learn":[4.863587157],"iteration":177,"passed_time":0.5583681518,"remaining_time":2.578531577},
{"learn":[4.858028614],"iteration":178,"passed_time":0.5595931335,"remaining_time":2.566625489},
{"learn":[4.853838176],"iteration":179,"passed_time":0.5615934414,"remaining_time":2.558370122},
{"learn":[4.853462329],"iteration":180,"passed_time":0.5622813313,"remaining_time":2.544245361},
{"learn":[4.851573196],"iteration":181,"passed_time":0.563711611,"remaining_time":2.533604933},
{"learn":[4.848442087],"iteration":182,"passed_time":0.5653174323,"remaining_time":2.523848865},
{"learn":[4.845547104],"iteration":183,"passed_time":0.568199697,"remaining_time":2.519842134},
{"learn":[4.839868817],"iteration":184,"passed_time":0.5696384152,"remaining_time":2.509488153},
{"learn":[4.836336958],"iteration":185,"passed_time":0.5709745692,"remaining_time":2.498781179},
{"learn":[4.831124789],"iteration":186,"passed_time":0.5722767949,"remaining_time":2.488026921},
{"learn":[4.827407333],"iteration":187,"passed_time":0.5741936216,"remaining_time":2.48002777},
{"learn":[4.824088918],"iteration":188,"passed_time":0.5755644483,"remaining_time":2.469750093},
{"learn":[4.820934539],"iteration":189,"passed_time":0.576901644,"remaining_time":2.459422798},
{"learn":[4.816975227],"iteration":190,"passed_time":0.5781970704,"remaining_time":2.449012722},
{"learn":[4.812340486],"iteration":191,"passed_time":0.5797571907,"remaining_time":2.439811511},
{"learn":[4.806402747],"iteration":192,"passed_time":0.5833065401,"remaining_time":2.439007139},
{"learn":[4.801521788],"iteration":193,"passed_time":0.58489104,"remaining_time":2.430011228},
{"learn":[4.797601172],"iteration":194,"passed_time":0.5862408347,"remaining_time":2.42012242},
{"learn":[4.792694629],"iteration":195,"passed_time":0.5874976074,"remaining_time":2.409939165},
{"learn":[4.789794613],"iteration":196,"passed_time":0.5887224122,"remaining_time":2.399716228},
{"learn":[4.785367055],"iteration":197,"passed_time":0.5899921157,"remaining_time":2.389766044},
{"learn":[4.780376856],"iteration":198,"passed_time":0.5913377433,"remaining_time":2.380208706},
{"learn":[4.776691261],"iteration":199,"passed_time":0.5926386729,"remaining_time":2.370554692},
{"learn":[4.773470753],"iteration":200,"passed_time":0.5940052177,"remaining_time":2.361244621},
{"learn":[4.77207327],"iteration":201,"passed_time":0.5953300905,"remaining_time":2.351848575},
{"learn":[4.767347177],"iteration":202,"passed_time":0.5974302001,"remaining_time":2.345575712},
{"learn":[4.763983068],"iteration":203,"passed_time":0.5986938042,"remaining_time":2.336079746},
{"learn":[4.761588849],"iteration":204,"passed_time":0.5999233285,"remaining_time":2.326531933},
{"learn":[4.758558086],"iteration":205,"passed_time":0.601221209,"remaining_time":2.317328349},
{"learn":[4.753678804],"iteration":206,"passed_time":0.6027782223,"remaining_time":2.309193866},
{"learn":[4.746510889],"iteration":207,"passed_time":0.6043669425,"remaining_time":2.301243358},
{"learn":[4.744840601],"iteration":208,"passed_time":0.6057069546,"remaining_time":2.292412445},
{"learn":[4.741702222],"iteration":209,"passed_time":0.6071033039,"remaining_time":2.28386481},
{"learn":[4.739352853],"iteration":210,"passed_time":0.608537278,"remaining_time":2.275525651},
{"learn":[4.735539287],"iteration":211,"passed_time":0.6100177064,"remaining_time":2.267424305},
{"learn":[4.730726751],"iteration":212,"passed_time":0.6113095387,"remaining_time":2.258688296},
{"learn":[4.726416092],"iteration":213,"passed_time":0.6128278388,"remaining_time":2.250853651},
{"learn":[4.721293082],"iteration":214,"passed_time":0.6142531691,"remaining_time":2.242738315},
{"learn":[4.718443695],"iteration":215,"passed_time":0.6153752918,"remaining_time":2.233584392},
{"learn":[4.711627962],"iteration":216,"passed_time":0.616566013,"remaining_time":2.224752019},
{"learn":[4.709790764],"iteration":217,"passed_time":0.6182595663,"remaining_time":2.21779349},
{"learn":[4.706913073],"iteration":218,"passed_time":0.6198932698,"remaining_time":2.210669606},
{"learn":[4.703846389],"iteration":219,"passed_time":0.6211824831,"remaining_time":2.202374258},
{"learn":[4.701001135],"iteration":220,"passed_time":0.6225286837,"remaining_time":2.194343188},
{"learn":[4.700380864],"iteration":221,"passed_time":0.6238283525,"remaining_time":2.186209271},
{"learn":[4.695837486],"iteration":222,"passed_time":0.6247644488,"remaining_time":2.176869851},
{"learn":[4.691242996],"iteration":223,"passed_time":0.6276570549,"remaining_time":2.174383369},
{"learn":[4.690284609],"iteration":224,"passed_time":0.6287875312,"remaining_time":2.165823718},
{"learn":[4.68827119],"iteration":225,"passed_time":0.6300254245,"remaining_time":2.157697693},
{"learn":[4.686922425],"iteration":226,"passed_time":0.631149858,"remaining_time":2.149245992},
{"learn":[4.686085874],"iteration":227,"passed_time":0.6321182838,"remaining_time":2.140330329},
{"learn":[4.683230741],"iteration":228,"passed_time":0.6330968715,"remaining_time":2.131518288},
{"learn":[4.6773487],"iteration":229,"passed_time":0.6341470493,"remaining_time":2.123014035},
{"learn":[4.671462906],"iteration":230,"passed_time":0.6351129311,"remaining_time":2.114293697},
{"learn":[4.664799601],"iteration":231,"passed_time":0.6361415847,"remaining_time":2.105848005},
{"learn":[4.660979386],"iteration":232,"passed_time":0.6370277309,"remaining_time":2.096996865},
{"learn":[4.656281279],"iteration":233,"passed_time":0.6380035839,"remaining_time":2.088507458},
{"learn":[4.651997094],"iteration":234,"passed_time":0.6389131309,"remaining_time":2.07986615},
{"learn":[4.650151977],"iteration":235,"passed_time":0.6398743698,"remaining_time":2.071457706},
{"learn":[4.648478046],"iteration":236,"passed_time":0.6420605533,"remaining_time":2.067055705},
{"learn":[4.646364602],"iteration":237,"passed_time":0.6432527813,"remaining_time":2.059489997},
{"learn":[4.642635873],"iteration":238,"passed_time":0.6442218358,"remaining_time":2.051267017},
{"learn":[4.640860821],"iteration":239,"passed_time":0.6451422501,"remaining_time":2.042950459},
{"learn":[4.639446822],"iteration":240,"passed_time":0.6459798243,"remaining_time":2.034434384},
{"learn":[4.637120072],"iteration":241,"passed_time":0.646915695,"remaining_time":2.026289656},
{"learn":[4.633769267],"iteration":242,"passed_time":0.6479317576,"remaining_time":2.018454076},
{"learn":[4.630491517],"iteration":243,"passed_time":0.6489300554,"remaining_time":2.010619352},
{"learn":[4.627813333],"iteration":244,"passed_time":0.649892503,"remaining_time":2.002729958},
{"learn":[4.622496304],"iteration":245,"passed_time":0.6509621631,"remaining_time":1.995225492},
{"learn":[4.618979301],"iteration":246,"passed_time":0.6518874964,"remaining_time":1.987333137},
{"learn":[4.616563458],"iteration":247,"passed_time":0.6530590533,"remaining_time":1.980243581},
{"learn":[4.614759385],"iteration":248,"passed_time":0.6540021714,"remaining_time":1.972512573},
{"learn":[4.61251363],"iteration":249,"passed_time":0.6549337743,"remaining_time":1.964801323},
{"learn":[4.608796693],"iteration":250,"passed_time":0.6564628026,"remaining_time":1.958926849},
{"learn":[4.60847774],"iteration":251,"passed_time":0.6573816879,"remaining_time":1.951275804},
{"learn":[4.605195659],"iteration":252,"passed_time":0.6583818011,"remaining_time":1.943917808},
{"learn":[4.60103766],"iteration":253,"passed_time":0.6593279678,"remaining_time":1.936451433},
{"learn":[4.599325598],"iteration":254,"passed_time":0.6602922424,"remaining_time":1.9290891},
{"learn":[4.597012808],"iteration":255,"passed_time":0.6614575117,"remaining_time":1.922360894},
{"learn":[4.594161533],"iteration":256,"passed_time":0.6625173398,"remaining_time":1.915371142},
{"learn":[4.592197259],"iteration":257,"passed_time":0.6634298705,"remaining_time":1.908003736},
{"learn":[4.58952828],"iteration":258,"passed_time":0.6647639193,"remaining_time":1.90189214},
{"learn":[4.585816572],"iteration":259,"passed_time":0.665941198,"remaining_time":1.895371102},
{"learn":[4.582934052],"iteration":260,"passed_time":0.6672496659,"remaining_time":1.889262464},
{"learn":[4.582234842],"iteration":261,"passed_time":0.6682063642,"remaining_time":1.882199606},
{"learn":[4.57571562],"iteration":262,"passed_time":0.6691824038,"remaining_time":1.875237382},
{"learn":[4.571197349],"iteration":263,"passed_time":0.6711211865,"remaining_time":1.87100452},
{"learn":[4.56723703],"iteration":264,"passed_time":0.6724942374,"remaining_time":1.865219866},
{"learn":[4.560335567],"iteration":265,"passed_time":0.6737785605,"remaining_time":1.859223547},
{"learn":[4.554709345],"iteration":266,"passed_time":0.6748533682,"remaining_time":1.852687337},
{"learn":[4.552806306],"iteration":267,"passed_time":0.6757979585,"remaining_time":1.845836215},
{"learn":[4.550766241],"iteration":268,"passed_time":0.6768015226,"remaining_time":1.839189268},
{"learn":[4.549216045],"iteration":269,"passed_time":0.6779877066,"remaining_time":1.833077873},
{"learn":[4.547687452],"iteration":270,"passed_time":0.6789709951,"remaining_time":1.826457031},
{"learn":[4.545642435],"iteration":271,"passed_time":0.6801048052,"remaining_time":1.820280508},
{"learn":[4.543930359],"iteration":272,"passed_time":0.6810437654,"remaining_time":1.813622042},
{"learn":[4.541029943],"iteration":273,"passed_time":0.6820186807,"remaining_time":1.807100592},
{"learn":[4.537781449],"iteration":274,"passed_time":0.6831383335,"remaining_time":1.801001061},
{"learn":[4.53066128],"iteration":275,"passed_time":0.6842909461,"remaining_time":1.795024076},
{"learn":[4.526763956],"iteration":276,"passed_time":0.6861178237,"remaining_time":1.790841829},
{"learn":[4.522036004],"iteration":277,"passed_time":0.6873894188,"remaining_time":1.78523439},
{"learn":[4.515307629],"iteration":278,"passed_time":0.6886318252,"remaining_time":1.779582602},
{"learn":[4.51109143],"iteration":279,"passed_time":0.6898382406,"remaining_time":1.773869761},
{"learn":[4.508233494],"iteration":280,"passed_time":0.6910051775,"remaining_time":1.768087981},
{"learn":[4.502555629],"iteration":281,"passed_time":0.6922742131,"remaining_time":1.762598883},
{"learn":[4.500081355],"iteration":282,"passed_time":0.6933896772,"remaining_time":1.756750525},
{"learn":[4.495281743],"iteration":283,"passed_time":0.6945274629,"remaining_time":1.750991773},
{"learn":[4.492138869],"iteration":284,"passed_time":0.6956796658,"remaining_time":1.745301618},
{"learn":[4.491708261],"iteration":285,"passed_time":0.6967411584,"remaining_time":1.739416738},
{"learn":[4.489398865],"iteration":286,"passed_time":0.6978748653,"remaining_time":1.733744874},
{"learn":[4.485796373],"iteration":287,"passed_time":0.6990750381,"remaining_time":1.728268844},
{"learn":[4.479542205],"iteration":288,"passed_time":0.7007875682,"remaining_time":1.72408291},
{"learn":[4.475986993],"iteration":289,"passed_time":0.7020311138,"remaining_time":1.71876583},
{"learn":[4.468661855],"iteration":290,"passed_time":0.7032403363,"remaining_time":1.713393122},
{"learn":[4.463785664],"iteration":291,"passed_time":0.7043612407,"remaining_time":1.707834789},
{"learn":[4.460445831],"iteration":292,"passed_time":0.7055421073,"remaining_time":1.702451433},
{"learn":[4.45692492],"iteration":293,"passed_time":0.706832095,"remaining_time":1.697358704},
{"learn":[4.454031688],"iteration":294,"passed_time":0.7079991935,"remaining_time":1.691998073},
{"learn":[4.451672391],"iteration":295,"passed_time":0.7090780121,"remaining_time":1.686455813},
{"learn":[4.45031553],"iteration":296,"passed_time":0.7101040543,"remaining_time":1.680818687},
{"learn":[4.446782666],"iteration":297,"passed_time":0.7111045247,"remaining_time":1.67515227},
{"learn":[4.444369689],"iteration":298,"passed_time":0.7120611564,"remaining_time":1.669414283},
{"learn":[4.44411683],"iteration":299,"passed_time":0.7129330886,"remaining_time":1.66351054},
{"learn":[4.440876943],"iteration":300,"passed_time":0.7138697192,"remaining_time":1.657790477},
{"learn":[4.439336453],"iteration":301,"passed_time":0.71545246,"remaining_time":1.653595421},
{"learn":[4.436666901],"iteration":302,"passed_time":0.7164413869,"remaining_time":1.648051639},
{"learn":[4.433043336],"iteration":303,"passed_time":0.7173954746,"remaining_time":1.64245806},
{"learn":[4.431419305],"iteration":304,"passed_time":0.7184262967,"remaining_time":1.637069758},
{"learn":[4.428859646],"iteration":305,"passed_time":0.7194441472,"remaining_time":1.631680517},
{"learn":[4.424552441],"iteration":306,"passed_time":0.7204250982,"remaining_time":1.626236459},
{"learn":[4.422706391],"iteration":307,"passed_time":0.7213285054,"remaining_time":1.620647162},
{"learn":[4.421427994],"iteration":308,"passed_time":0.7224615153,"remaining_time":1.615601641},
{"learn":[4.418733158],"iteration":309,"passed_time":0.7234518305,"remaining_time":1.610263752},
{"learn":[4.415656941],"iteration":310,"passed_time":0.7243938901,"remaining_time":1.604846914},
{"learn":[4.410747417],"iteration":311,"passed_time":0.7253209571,"remaining_time":1.5994257},
{"learn":[4.408126521],"iteration":312,"passed_time":0.7267207623,"remaining_time":1.595070811},
{"learn":[4.407843853],"iteration":313,"passed_time":0.7276808994,"remaining_time":1.589774194},
{"learn":[4.405219398],"iteration":314,"passed_time":0.7299338998,"remaining_time":1.587316576},
{"learn":[4.402708465],"iteration":315,"passed_time":0.7311863127,"remaining_time":1.582694424},
{"learn":[4.40104971],"iteration":316,"passed_time":0.7321911325,"remaining_time":1.577560074},
{"learn":[4.400830038],"iteration":317,"passed_time":0.7333248469,"remaining_time":1.572728131},
{"learn":[4.39784288],"iteration":318,"passed_time":0.7344727928,"remaining_time":1.567949755},
{"learn":[4.393741845],"iteration":319,"passed_time":0.7354417141,"remaining_time":1.562813642},
{"learn":[4.393425936],"iteration":320,"passed_time":0.7365576658,"remaining_time":1.558014502},
{"learn":[4.390505974],"iteration":321,"passed_time":0.7378763252,"remaining_time":1.553665057},
{"learn":[4.390305136],"iteration":322,"passed_time":0.739057325,"remaining_time":1.549045848},
{"learn":[4.38568203],"iteration":323,"passed_time":0.7401108475,"remaining_time":1.544181892},
{"learn":[4.383057135],"iteration":324,"passed_time":0.7410534326,"remaining_time":1.539110975},
{"learn":[4.380662684],"iteration":325,"passed_time":0.7422731947,"remaining_time":1.534638445},
{"learn":[4.37805727],"iteration":326,"passed_time":0.7434856749,"remaining_time":1.530170823},
{"learn":[4.373708319],"iteration":327,"passed_time":0.7451155266,"remaining_time":1.526578152},
{"learn":[4.36887921],"iteration":328,"passed_time":0.7461940783,"remaining_time":1.521873029},
{"learn":[4.367895929],"iteration":329,"passed_time":0.7470756012,"remaining_time":1.516789857},
{"learn":[4.362140573],"iteration":330,"passed_time":0.7480022968,"remaining_time":1.511823373},
{"learn":[4.361931924],"iteration":331,"passed_time":0.7489192735,"remaining_time":1.506861671},
{"learn":[4.359656377],"iteration":332,"passed_time":0.7498568725,"remaining_time":1.501965568},
{"learn":[4.354281355],"iteration":333,"passed_time":0.750814957,"remaining_time":1.497134016},
{"learn":[4.348589447],"iteration":334,"passed_time":0.7517684817,"remaining_time":1.492316538},
{"learn":[4.346355698],"iteration":335,"passed_time":0.7526404556,"remaining_time":1.4873609},
{"learn":[4.343894047],"iteration":336,"passed_time":0.753679386,"remaining_time":1.482757961},
{"learn":[4.341561356],"iteration":337,"passed_time":0.7546108815,"remaining_time":1.477965691},
{"learn":[4.338869061],"iteration":338,"passed_time":0.7555499949,"remaining_time":1.473211052},
{"learn":[4.333720063],"iteration":339,"passed_time":0.7565092802,"remaining_time":1.468518014},
{"learn":[4.330892223],"iteration":340,"passed_time":0.7574451917,"remaining_time":1.463801705},
{"learn":[4.328311474],"iteration":341,"passed_time":0.7594030095,"remaining_time":1.461073627},
{"learn":[4.324580133],"iteration":342,"passed_time":0.7604559491,"remaining_time":1.456616789},
{"learn":[4.323354432],"iteration":343,"passed_time":0.761365253,"remaining_time":1.451905831},
{"learn":[4.323159553],"iteration":344,"passed_time":0.7622019853,"remaining_time":1.447079132},
{"learn":[4.318639682],"iteration":345,"passed_time":0.7631496701,"remaining_time":1.442485215},
{"learn":[4.312712208],"iteration":346,"passed_time":0.7640102879,"remaining_time":1.437748467},
{"learn":[4.311461062],"iteration":347,"passed_time":0.7651711979,"remaining_time":1.433596612},
{"learn":[4.311178356],"iteration":348,"passed_time":0.7661233511,"remaining_time":1.429072497},
{"learn":[4.311102505],"iteration":349,"passed_time":0.7673087112,"remaining_time":1.425001892},
{"learn":[4.310232308],"iteration":350,"passed_time":0.7685463372,"remaining_time":1.421044367},
{"learn":[4.305128197],"iteration":351,"passed_time":0.7698535951,"remaining_time":1.417230482},
{"learn":[4.304595496],"iteration":352,"passed_time":0.7709398892,"remaining_time":1.413025803},
{"learn":[4.3004992],"iteration":353,"passed_time":0.7720641895,"remaining_time":1.408908097},
{"learn":[4.297581524],"iteration":354,"passed_time":0.7741531266,"remaining_time":1.406559906},
{"learn":[4.297355825],"iteration":355,"passed_time":0.7754111343,"remaining_time":1.40271003},
{"learn":[4.295758715],"iteration":356,"passed_time":0.7764169259,"remaining_time":1.398420402},
{"learn":[4.292500657],"iteration":357,"passed_time":0.7776426692,"remaining_time":1.394543558},
{"learn":[4.290797586],"iteration":358,"passed_time":0.7788054212,"remaining_time":1.390569011},
{"learn":[4.286410608],"iteration":359,"passed_time":0.779944665,"remaining_time":1.386568293},
{"learn":[4.280278245],"iteration":360,"passed_time":0.7810247294,"remaining_time":1.382478676},
{"learn":[4.279941283],"iteration":361,"passed_time":0.782101564,"remaining_time":1.378399994},
{"learn":[4.274426275],"iteration":362,"passed_time":0.7832486001,"remaining_time":1.374461042},
{"learn":[4.273567658],"iteration":363,"passed_time":0.7842595514,"remaining_time":1.370299656},
{"learn":[4.269488271],"iteration":364,"passed_time":0.7854242774,"remaining_time":1.366423058},
{"learn":[4.266838205],"iteration":365,"passed_time":0.7865272941,"remaining_time":1.362454384},
{"learn":[4.263456509],"iteration":366,"passed_time":0.7876119052,"remaining_time":1.35846958},
{"learn":[4.260360204],"iteration":367,"passed_time":0.7893767439,"remaining_time":1.355668756},
{"learn":[4.255120549],"iteration":368,"passed_time":0.7906032337,"remaining_time":1.351952955},
{"learn":[4.252582211],"iteration":369,"passed_time":0.7916517647,"remaining_time":1.347947599},
{"learn":[4.247857931],"iteration":370,"passed_time":0.7926264144,"remaining_time":1.343832924},
{"learn":[4.245288911],"iteration":371,"passed_time":0.7937886226,"remaining_time":1.340051761},
{"learn":[4.24048515],"iteration":372,"passed_time":0.7949679007,"remaining_time":1.336313334},
{"learn":[4.2378365],"iteration":373,"passed_time":0.7960226474,"remaining_time":1.332380153},
{"learn":[4.236751063],"iteration":374,"passed_time":0.7971602457,"remaining_time":1.328600409},
{"learn":[4.233240093],"iteration":375,"passed_time":0.7981373769,"remaining_time":1.324568413},
{"learn":[4.230358421],"iteration":376,"passed_time":0.799157246,"remaining_time":1.320623247},
{"learn":[4.225853583],"iteration":377,"passed_time":0.8003269047,"remaining_time":1.316940039},
{"learn":[4.224702126],"iteration":378,"passed_time":0.8015797045,"remaining_time":1.313406323},
{"learn":[4.224361982],"iteration":379,"passed_time":0.8038471054,"remaining_time":1.311540014},
{"learn":[4.223787954],"iteration":380,"passed_time":0.8050484731,"remaining_time":1.307939645},
{"learn":[4.22144054],"iteration":381,"passed_time":0.8062869194,"remaining_time":1.304411822},
{"learn":[4.217739335],"iteration":382,"passed_time":0.8073671003,"remaining_time":1.300640995},
{"learn":[4.215611665],"iteration":383,"passed_time":0.8084196244,"remaining_time":1.296839814},
{"learn":[4.210236863],"iteration":384,"passed_time":0.8094118865,"remaining_time":1.29295665},
{"learn":[4.208454294],"iteration":385,"passed_time":0.8106488538,"remaining_time":1.28947771},
{"learn":[4.207446501],"iteration":386,"passed_time":0.8116120583,"remaining_time":1.285576723},
{"learn":[4.204985442],"iteration":387,"passed_time":0.8125464776,"remaining_time":1.281645475},
{"learn":[4.202796622],"iteration":388,"passed_time":0.8138234971,"remaining_time":1.278267755},
{"learn":[4.199774004],"iteration":389,"passed_time":0.8147730273,"remaining_time":1.274388581},
{"learn":[4.199458358],"iteration":390,"passed_time":0.8157034136,"remaining_time":1.270494575},
{"learn":[4.19751254],"iteration":391,"passed_time":0.8168159964,"remaining_time":1.26689828},
{"learn":[4.195201346],"iteration":392,"passed_time":0.8184143552,"remaining_time":1.26406492},
{"learn":[4.190593508],"iteration":393,"passed_time":0.8196433332,"remaining_time":1.260669695},
{"learn":[4.187212054],"iteration":394,"passed_time":0.820708594,"remaining_time":1.257034682},
{"learn":[4.184984466],"iteration":395,"passed_time":0.8216991148,"remaining_time":1.25329865},
{"learn":[4.182832144],"iteration":396,"passed_time":0.8226036654,"remaining_time":1.24944587},
{"learn":[4.179752812],"iteration":397,"passed_time":0.8237386655,"remaining_time":1.245956474},
{"learn":[4.17878934],"iteration":398,"passed_time":0.8249228185,"remaining_time":1.242552917},
{"learn":[4.174548229],"iteration":399,"passed_time":0.8259234122,"remaining_time":1.238885118},
{"learn":[4.168872556],"iteration":400,"passed_time":0.826868184,"remaining_time":1.235147237},
{"learn":[4.163926494],"iteration":401,"passed_time":0.827971018,"remaining_time":1.23165838},
{"learn":[4.159485076],"iteration":402,"passed_time":0.8291803946,"remaining_time":1.228339195},
{"learn":[4.155926102],"iteration":403,"passed_time":0.8302100117,"remaining_time":1.224765265},
{"learn":[4.153540115],"iteration":404,"passed_time":0.8312583666,"remaining_time":1.221231428},
{"learn":[4.150983044],"iteration":405,"passed_time":0.8330903664,"remaining_time":1.218856349},
{"learn":[4.146539132],"iteration":406,"passed_time":0.834347038,"remaining_time":1.215645684},
{"learn":[4.144869174],"iteration":407,"passed_time":0.8354849044,"remaining_time":1.212272214},
{"learn":[4.142825962],"iteration":408,"passed_time":0.8366661416,"remaining_time":1.208972346},
{"learn":[4.142467378],"iteration":409,"passed_time":0.8380299258,"remaining_time":1.205945503},
{"learn":[4.141800768],"iteration":410,"passed_time":0.8390742682,"remaining_time":1.202468963},
{"learn":[4.140107084],"iteration":411,"passed_time":0.8403446013,"remaining_time":1.199326761},
{"learn":[4.136243196],"iteration":412,"passed_time":0.8414856396,"remaining_time":1.196009856},
{"learn":[4.133618439],"iteration":413,"passed_time":0.8425147633,"remaining_time":1.192545051},
{"learn":[4.131053025],"iteration":414,"passed_time":0.8436405046,"remaining_time":1.189228181},
{"learn":[4.128379975],"iteration":415,"passed_time":0.8448321335,"remaining_time":1.186014341},
{"learn":[4.127068571],"iteration":416,"passed_time":0.84653753,"remaining_time":1.183528489},
{"learn":[4.125969877],"iteration":417,"passed_time":0.8482596291,"remaining_time":1.181069627},
{"learn":[4.123893633],"iteration":418,"passed_time":0.8495434322,"remaining_time":1.178006525},
{"learn":[4.119643722],"iteration":419,"passed_time":0.8512759689,"remaining_time":1.175571576},
{"learn":[4.11465686],"iteration":420,"passed_time":0.8527402134,"remaining_time":1.172770982},
{"learn":[4.111565986],"iteration":421,"passed_time":0.8540167308,"remaining_time":1.169719598},
{"learn":[4.106322452],"iteration":422,"passed_time":0.8555363404,"remaining_time":1.1670082},
{"learn":[4.104222175],"iteration":423,"passed_time":0.856713712,"remaining_time":1.163837496},
{"learn":[4.103008002],"iteration":424,"passed_time":0.8576774653,"remaining_time":1.160387159},
{"learn":[4.099176337],"iteration":425,"passed_time":0.8587039609,"remaining_time":1.157033036},
{"learn":[4.096525716],"iteration":426,"passed_time":0.8598384189,"remaining_time":1.153834693},
{"learn":[4.094967724],"iteration":427,"passed_time":0.8609060422,"remaining_time":1.150556673},
{"learn":[4.094683584],"iteration":428,"passed_time":0.8630440463,"remaining_time":1.148713637},
{"learn":[4.091096563],"iteration":429,"passed_time":0.864475329,"remaining_time":1.145932413},
{"learn":[4.089178677],"iteration":430,"passed_time":0.8659198523,"remaining_time":1.143174933},
{"learn":[4.085335077],"iteration":431,"passed_time":0.8676296419,"remaining_time":1.140772307},
{"learn":[4.084852122],"iteration":432,"passed_time":0.8691725348,"remaining_time":1.138154335},
{"learn":[4.080322952],"iteration":433,"passed_time":0.8704630547,"remaining_time":1.135212187},
{"learn":[4.077449519],"iteration":434,"passed_time":0.8716192123,"remaining_time":1.132103115},
{"learn":[4.076568374],"iteration":435,"passed_time":0.8734921195,"remaining_time":1.129930173},
{"learn":[4.076071793],"iteration":436,"passed_time":0.8748923094,"remaining_time":1.127149589},
{"learn":[4.075027644],"iteration":437,"passed_time":0.87602963,"remaining_time":1.124038018},
{"learn":[4.07020837],"iteration":438,"passed_time":0.8780644828,"remaining_time":1.122082403},
{"learn":[4.06833694],"iteration":439,"passed_time":0.8792118417,"remaining_time":1.118996889},
{"learn":[4.063936568],"iteration":440,"passed_time":0.8806927972,"remaining_time":1.116343024},
{"learn":[4.061734926],"iteration":441,"passed_time":0.8819706099,"remaining_time":1.11343801},
{"learn":[4.060815619],"iteration":442,"passed_time":0.8831088078,"remaining_time":1.110364799},
{"learn":[4.056407489],"iteration":443,"passed_time":0.8845376722,"remaining_time":1.107664292},
{"learn":[4.05238936],"iteration":444,"passed_time":0.8856787289,"remaining_time":1.10461055},
{"learn":[4.049685254],"iteration":445,"passed_time":0.8867672377,"remaining_time":1.101500111},
{"learn":[4.045162016],"iteration":446,"passed_time":0.8879203278,"remaining_time":1.098478616},
{"learn":[4.042955482],"iteration":447,"passed_time":0.8889011647,"remaining_time":1.095253221},
{"learn":[4.041467663],"iteration":448,"passed_time":0.8899010389,"remaining_time":1.092061186},
{"learn":[4.038920476],"iteration":449,"passed_time":0.8911002294,"remaining_time":1.089122503},
{"learn":[4.036694383],"iteration":450,"passed_time":0.8929041314,"remaining_time":1.086927646},
{"learn":[4.034999007],"iteration":451,"passed_time":0.8943158248,"remaining_time":1.084259009},
{"learn":[4.031928018],"iteration":452,"passed_time":0.8954132214,"remaining_time":1.081216406},
{"learn":[4.028718143],"iteration":453,"passed_time":0.8966305219,"remaining_time":1.078326575},
{"learn":[4.027401978],"iteration":454,"passed_time":0.8980421345,"remaining_time":1.075676842},
{"learn":[4.025930598],"iteration":455,"passed_time":0.8990526652,"remaining_time":1.072554057},
{"learn":[4.021074523],"iteration":456,"passed_time":0.9002013239,"remaining_time":1.069604637},
{"learn":[4.020268486],"iteration":457,"passed_time":0.9012385123,"remaining_time":1.066531165},
{"learn":[4.017986361],"iteration":458,"passed_time":0.9023165277,"remaining_time":1.063514687},
{"learn":[4.014814804],"iteration":459,"passed_time":0.9032830369,"remaining_time":1.060375739},
{"learn":[4.009704796],"iteration":460,"passed_time":0.904334127,"remaining_time":1.057345107},
{"learn":[4.008440457],"iteration":461,"passed_time":0.9052898652,"remaining_time":1.054212008},
{"learn":[4.004854849],"iteration":462,"passed_time":0.906701738,"remaining_time":1.051617351},
{"learn":[4.000898028],"iteration":463,"passed_time":0.9081324561,"remaining_time":1.049049561},
{"learn":[3.996617985],"iteration":464,"passed_time":0.9091242677,"remaining_time":1.045981684},
{"learn":[3.995443319],"iteration":465,"passed_time":0.9101033642,"remaining_time":1.042908147},
{"learn":[3.990771995],"iteration":466,"passed_time":0.9112722885,"remaining_time":1.040060235},
{"learn":[3.989249359],"iteration":467,"passed_time":0.9122036341,"remaining_time":1.03694943},
{"learn":[3.986599538],"iteration":468,"passed_time":0.9134086255,"remaining_time":1.03415774},
{"learn":[3.985628919],"iteration":469,"passed_time":0.9145080177,"remaining_time":1.031253722},
{"learn":[3.985086112],"iteration":470,"passed_time":0.9154322834,"remaining_time":1.028160675},
{"learn":[3.98466839],"iteration":471,"passed_time":0.916371386,"remaining_time":1.025093415},
{"learn":[3.984233894],"iteration":472,"passed_time":0.9173245635,"remaining_time":1.022050835},
{"learn":[3.981855845],"iteration":473,"passed_time":0.9182887556,"remaining_time":1.019029294},
{"learn":[3.978684264],"iteration":474,"passed_time":0.9192823843,"remaining_time":1.016048951},
{"learn":[3.974361269],"iteration":475,"passed_time":0.9205795519,"remaining_time":1.013411103},
{"learn":[3.972074049],"iteration":476,"passed_time":0.9223459569,"remaining_time":1.011293366},
{"learn":[3.97191982],"iteration":477,"passed_time":0.9234876514,"remaining_time":1.008494883},
{"learn":[3.969616848],"iteration":478,"passed_time":0.9246351168,"remaining_time":1.005709595},
{"learn":[3.968533527],"iteration":479,"passed_time":0.9255893511,"remaining_time":1.002721797},
{"learn":[3.967568753],"iteration":480,"passed_time":0.9264840079,"remaining_time":0.9996781707},
{"learn":[3.966232553],"iteration":481,"passed_time":0.9274472216,"remaining_time":0.9967171386},
{"learn":[3.961522393],"iteration":482,"passed_time":0.9283892696,"remaining_time":0.9937417233},
{"learn":[3.955829553],"iteration":483,"passed_time":0.9292869501,"remaining_time":0.9907274096},
{"learn":[3.954248095],"iteration":484,"passed_time":0.9302417044,"remaining_time":0.9877824284},
{"learn":[3.951922606],"iteration":485,"passed_time":0.9314670388,"remaining_time":0.9851318064},
{"learn":[3.94978202],"iteration":486,"passed_time":0.9324210865,"remaining_time":0.9822012677},
{"learn":[3.949518999],"iteration":487,"passed_time":0.9333793878,"remaining_time":0.9792832922},
{"learn":[3.945431216],"iteration":488,"passed_time":0.9344850818,"remaining_time":0.9765273555},
{"learn":[3.943249086],"iteration":489,"passed_time":0.9354753753,"remaining_time":0.9736580437},
{"learn":[3.941981548],"iteration":490,"passed_time":0.9372409072,"remaining_time":0.9716000443},
{"learn":[3.936600517],"iteration":491,"passed_time":0.9384692053,"remaining_time":0.9689885291},
{"learn":[3.934476885],"iteration":492,"passed_time":0.9393888235,"remaining_time":0.9660651795},
{"learn":[3.93045798],"iteration":493,"passed_time":0.9402964027,"remaining_time":0.9631376109},
{"learn":[3.925977375],"iteration":494,"passed_time":0.9413744706,"remaining_time":0.9603921367},
{"learn":[3.92457993],"iteration":495,"passed_time":0.942505489,"remaining_time":0.9577071905},
{"learn":[3.919849146],"iteration":496,"passed_time":0.9434992517,"remaining_time":0.9548895847},
{"learn":[3.919681964],"iteration":497,"passed_time":0.9446300382,"remaining_time":0.9522174281},
{"learn":[3.917633027],"iteration":498,"passed_time":0.9455715307,"remaining_time":0.9493613966},
{"learn":[3.916616419],"iteration":499,"passed_time":0.946467913,"remaining_time":0.946467913},
{"learn":[3.912896166],"iteration":500,"passed_time":0.9473608918,"remaining_time":0.943579012},
{"learn":[3.912769674],"iteration":501,"passed_time":0.9483171896,"remaining_time":0.9407608774},
{"learn":[3.909373788],"iteration":502,"passed_time":0.9494584536,"remaining_time":0.9381329055},
{"learn":[3.906706036],"iteration":503,"passed_time":0.9508594971,"remaining_time":0.9357664892},
{"learn":[3.903895664],"iteration":504,"passed_time":0.9524958945,"remaining_time":0.9336345897},
{"learn":[3.902982967],"iteration":505,"passed_time":0.9537336534,"remaining_time":0.931115464},
{"learn":[3.900905528],"iteration":506,"passed_time":0.9548872457,"remaining_time":0.9285195505},
{"learn":[3.897463465],"iteration":507,"passed_time":0.9562607704,"remaining_time":0.926142321},
{"learn":[3.895918033],"iteration":508,"passed_time":0.9575452563,"remaining_time":0.9236831451},
{"learn":[3.893921936],"iteration":509,"passed_time":0.9586599918,"remaining_time":0.9210654823},
{"learn":[3.890237934],"iteration":510,"passed_time":0.9596612075,"remaining_time":0.9183450694},
{"learn":[3.887311613],"iteration":511,"passed_time":0.9608902509,"remaining_time":0.9158485204},
{"learn":[3.884869735],"iteration":512,"passed_time":0.9620707652,"remaining_time":0.9133108434},
{"learn":[3.882101231],"iteration":513,"passed_time":0.9630054859,"remaining_time":0.9105460431},
{"learn":[3.88060368],"iteration":514,"passed_time":0.9641086675,"remaining_time":0.9079469976},
{"learn":[3.877726076],"iteration":515,"passed_time":0.9650923382,"remaining_time":0.9052416506},
{"learn":[3.874938145],"iteration":516,"passed_time":0.9670358134,"remaining_time":0.9034396478},
{"learn":[3.874340833],"iteration":517,"passed_time":0.9682320511,"remaining_time":0.9009417927},
{"learn":[3.873105224],"iteration":518,"passed_time":0.9692699348,"remaining_time":0.8983021939},
{"learn":[3.869800236],"iteration":519,"passed_time":0.9702765445,"remaining_time":0.8956398873},
{"learn":[3.867932518],"iteration":520,"passed_time":0.9712533073,"remaining_time":0.8929564956},
{"learn":[3.866666962],"iteration":521,"passed_time":0.9722032255,"remaining_time":0.8902550609},
{"learn":[3.865527652],"iteration":522,"passed_time":0.9734598912,"remaining_time":0.887840092},
{"learn":[3.861900081],"iteration":523,"passed_time":0.9745229569,"remaining_time":0.8852536784},
{"learn":[3.858502887],"iteration":524,"passed_time":0.9757028775,"remaining_time":0.8827787939},
{"learn":[3.858335097],"iteration":525,"passed_time":0.9769611138,"remaining_time":0.8803794067},
{"learn":[3.855719306],"iteration":526,"passed_time":0.9779603034,"remaining_time":0.8777518473},
{"learn":[3.855137428],"iteration":527,"passed_time":0.978936654,"remaining_time":0.8751100392},
{"learn":[3.851985706],"iteration":528,"passed_time":0.9799447048,"remaining_time":0.8725027523},
{"learn":[3.851051809],"iteration":529,"passed_time":0.9818847554,"remaining_time":0.8707279906},
{"learn":[3.850679146],"iteration":530,"passed_time":0.9830251213,"remaining_time":0.8682462935},
{"learn":[3.848179484],"iteration":531,"passed_time":0.9840663934,"remaining_time":0.8656824663},
{"learn":[3.844551071],"iteration":532,"passed_time":0.9853681785,"remaining_time":0.8633526067},
{"learn":[3.841604794],"iteration":533,"passed_time":0.986457376,"remaining_time":0.8608410809},
{"learn":[3.83969656],"iteration":534,"passed_time":0.9877877054,"remaining_time":0.8585444542},
{"learn":[3.836811463],"iteration":535,"passed_time":0.9890304619,"remaining_time":0.8561756237},
{"learn":[3.834182551],"iteration":536,"passed_time":0.9900918251,"remaining_time":0.8536545903},
{"learn":[3.828012842],"iteration":537,"passed_time":0.9912588886,"remaining_time":0.8512297519},
{"learn":[3.826636176],"iteration":538,"passed_time":0.9922320743,"remaining_time":0.8486437593},
{"learn":[3.826189798],"iteration":539,"passed_time":0.9934696907,"remaining_time":0.8462889958},
{"learn":[3.824104738],"iteration":540,"passed_time":0.9944738044,"remaining_time":0.8437402518},
{"learn":[3.82300218],"iteration":541,"passed_time":0.996314149,"remaining_time":0.8419038381},
{"learn":[3.817146402],"iteration":542,"passed_time":0.9974445437,"remaining_time":0.8394699014},
{"learn":[3.814638044],"iteration":543,"passed_time":0.9985119909,"remaining_time":0.8369879923},
{"learn":[3.812979573],"iteration":544,"passed_time":0.9995147421,"remaining_time":0.8344572618},
{"learn":[3.811938825],"iteration":545,"passed_time":1.000381475,"remaining_time":0.8318190285},
{"learn":[3.811479418],"iteration":546,"passed_time":1.00134232,"remaining_time":0.8292652121},
{"learn":[3.80742981],"iteration":547,"passed_time":1.002355,"remaining_time":0.8267599633},
{"learn":[3.805097043],"iteration":548,"passed_time":1.003739062,"remaining_time":0.82456524},
{"learn":[3.801577232],"iteration":549,"passed_time":1.00480641,"remaining_time":0.8221143351},
{"learn":[3.799762083],"iteration":550,"passed_time":1.005901151,"remaining_time":0.8196907749},
{"learn":[3.796393455],"iteration":551,"passed_time":1.006906961,"remaining_time":0.8171998527},
{"learn":[3.793486459],"iteration":552,"passed_time":1.007832452,"remaining_time":0.814649378},
{"learn":[3.792006091],"iteration":553,"passed_time":1.00899945,"remaining_time":0.8122991963},
{"learn":[3.78932128],"iteration":554,"passed_time":1.011170447,"remaining_time":0.8107582863},
{"learn":[3.787581812],"iteration":555,"passed_time":1.012318678,"remaining_time":0.8083983692},
{"learn":[3.785308865],"iteration":556,"passed_time":1.013318429,"remaining_time":0.8059247114},
{"learn":[3.78465475],"iteration":557,"passed_time":1.014193166,"remaining_time":0.8033573109},
{"learn":[3.780498869],"iteration":558,"passed_time":1.015178925,"remaining_time":0.8008835524},
{"learn":[3.778734909],"iteration":559,"passed_time":1.016184869,"remaining_time":0.7984309683},
{"learn":[3.778652349],"iteration":560,"passed_time":1.017284925,"remaining_time":0.7960571873},
{"learn":[3.777928006],"iteration":561,"passed_time":1.018421845,"remaining_time":0.7937166696},
{"learn":[3.776131406],"iteration":562,"passed_time":1.019589243,"remaining_time":0.7914040838},
{"learn":[3.772925617],"iteration":563,"passed_time":1.020623712,"remaining_time":0.7889927983},
{"learn":[3.7727745],"iteration":564,"passed_time":1.021620557,"remaining_time":0.78655742},
{"learn":[3.771763073],"iteration":565,"passed_time":1.022718772,"remaining_time":0.7842048536},
{"learn":[3.768738162],"iteration":566,"passed_time":1.023733729,"remaining_time":0.7817931299},
{"learn":[3.767220794],"iteration":567,"passed_time":1.02501149,"remaining_time":0.7795862034},
{"learn":[3.766691102],"iteration":568,"passed_time":1.026974977,"remaining_time":0.7779019599},
{"learn":[3.766259335],"iteration":569,"passed_time":1.028606063,"remaining_time":0.7759659777},
{"learn":[3.76116362],"iteration":570,"passed_time":1.029983179,"remaining_time":0.7738402518},
{"learn":[3.758633056],"iteration":571,"passed_time":1.031258298,"remaining_time":0.7716408245},
{"learn":[3.754603809],"iteration":572,"passed_time":1.032597316,"remaining_time":0.769492241},
{"learn":[3.754070549],"iteration":573,"passed_time":1.033783078,"remaining_time":0.7672327372},
{"learn":[3.750534319],"iteration":574,"passed_time":1.035019531,"remaining_time":0.7650144362},
{"learn":[3.746491516],"iteration":575,"passed_time":1.036376288,"remaining_time":0.7628881012},
{"learn":[3.744210544],"iteration":576,"passed_time":1.037563049,"remaining_time":0.7606398087},
{"learn":[3.742929991],"iteration":577,"passed_time":1.038843328,"remaining_time":0.7584634682},
{"learn":[3.740402992],"iteration":578,"passed_time":1.040780671,"remaining_time":0.7567679835},
{"learn":[3.739644243],"iteration":579,"passed_time":1.042230767,"remaining_time":0.7547188315},
{"learn":[3.737529404],"iteration":580,"passed_time":1.04346142,"remaining_time":0.7525134853},
{"learn":[3.737196923],"iteration":581,"passed_time":1.044612151,"remaining_time":0.7502540875},
{"learn":[3.733954464],"iteration":582,"passed_time":1.04584375,"remaining_time":0.7480563361},
{"learn":[3.731608623],"iteration":583,"passed_time":1.047008429,"remaining_time":0.7458142231},
{"learn":[3.729843952],"iteration":584,"passed_time":1.048724966,"remaining_time":0.7439672834},
{"learn":[3.727223798],"iteration":585,"passed_time":1.05010053,"remaining_time":0.7418798966},
{"learn":[3.725351667],"iteration":586,"passed_time":1.051299888,"remaining_time":0.7396709603},
{"learn":[3.725026912],"iteration":587,"passed_time":1.052388335,"remaining_time":0.7373877447},
{"learn":[3.721974565],"iteration":588,"passed_time":1.053388917,"remaining_time":0.7350472752},
{"learn":[3.720269493],"iteration":589,"passed_time":1.054727719,"remaining_time":0.7329463808},
{"learn":[3.718907466],"iteration":590,"passed_time":1.056526438,"remaining_time":0.7311663506},
{"learn":[3.715602912],"iteration":591,"passed_time":1.057695956,"remaining_time":0.7289526184},
{"learn":[3.714463059],"iteration":592,"passed_time":1.058710965,"remaining_time":0.7266363621},
{"learn":[3.710802077],"iteration":593,"passed_time":1.059748216,"remaining_time":0.7243396898},
{"learn":[3.708032435],"iteration":594,"passed_time":1.060756941,"remaining_time":0.7220278341},
{"learn":[3.703788939],"iteration":595,"passed_time":1.06189535,"remaining_time":0.7198082574},
{"learn":[3.702500944],"iteration":596,"passed_time":1.063020309,"remaining_time":0.7175832236},
{"learn":[3.698196925],"iteration":597,"passed_time":1.064114507,"remaining_time":0.7153411901},
{"learn":[3.69658891],"iteration":598,"passed_time":1.065296553,"remaining_time":0.7131617994},
{"learn":[3.696124066],"iteration":599,"passed_time":1.066298248,"remaining_time":0.7108654987},
{"learn":[3.693537052],"iteration":600,"passed_time":1.06729409,"remaining_time":0.7085696206},
{"learn":[3.691343275],"iteration":601,"passed_time":1.06834281,"remaining_time":0.7063130207},
{"learn":[3.690973831],"iteration":602,"passed_time":1.069633015,"remaining_time":0.7042194142},
{"learn":[3.686151073],"iteration":603,"passed_time":1.071319526,"remaining_time":0.7023882986},
{"learn":[3.683921982],"iteration":604,"passed_time":1.072421582,"remaining_time":0.7001760739},
{"learn":[3.679975271],"iteration":605,"passed_time":1.073565867,"remaining_time":0.6979949694},
{"learn":[3.674047638],"iteration":606,"passed_time":1.074899846,"remaining_time":0.6959400977},
{"learn":[3.673151794],"iteration":607,"passed_time":1.075865422,"remaining_time":0.6936500745},
{"learn":[3.670953108],"iteration":608,"passed_time":1.077046262,"remaining_time":0.6915026083},
{"learn":[3.6703947],"iteration":609,"passed_time":1.078114912,"remaining_time":0.6892865829},
{"learn":[3.668433805],"iteration":610,"passed_time":1.079133187,"remaining_time":0.6870422417},
{"learn":[3.668304956],"iteration":611,"passed_time":1.080066298,"remaining_time":0.6847479143},
{"learn":[3.667880012],"iteration":612,"passed_time":1.081003955,"remaining_time":0.6824608981},
{"learn":[3.667282264],"iteration":613,"passed_time":1.081993738,"remaining_time":0.6802110469},
{"learn":[3.664611483],"iteration":614,"passed_time":1.082935947,"remaining_time":0.6779355118},
{"learn":[3.662543394],"iteration":615,"passed_time":1.083986323,"remaining_time":0.6757317341},
{"learn":[3.659041959],"iteration":616,"passed_time":1.085627246,"remaining_time":0.6738982745},
{"learn":[3.656868545],"iteration":617,"passed_time":1.086694228,"remaining_time":0.6717106714},
{"learn":[3.654785614],"iteration":618,"passed_time":1.087755358,"remaining_time":0.6695230879},
{"learn":[3.654566096],"iteration":619,"passed_time":1.088952076,"remaining_time":0.6674222402},
{"learn":[3.651007045],"iteration":620,"passed_time":1.090043415,"remaining_time":0.665259991},
{"learn":[3.648921786],"iteration":621,"passed_time":1.091063144,"remaining_time":0.6630576661},
{"learn":[3.647655706],"iteration":622,"passed_time":1.092062246,"remaining_time":0.660846656},
{"learn":[3.647241144],"iteration":623,"passed_time":1.093041793,"remaining_time":0.6586277473},
{"learn":[3.644195689],"iteration":624,"passed_time":1.094156194,"remaining_time":0.6564937162},
{"learn":[3.642632246],"iteration":625,"passed_time":1.095096211,"remaining_time":0.6542587589},
{"learn":[3.642523322],"iteration":626,"passed_time":1.095974767,"remaining_time":0.6519913687},
{"learn":[3.641494659],"iteration":627,"passed_time":1.096969245,"remaining_time":0.6497970688},
{"learn":[3.63976496],"iteration":628,"passed_time":1.097955239,"remaining_time":0.6476015799},
{"learn":[3.637945652],"iteration":629,"passed_time":1.099375984,"remaining_time":0.6456652603},
{"learn":[3.636233667],"iteration":630,"passed_time":1.100335102,"remaining_time":0.6434606222},
{"learn":[3.635304404],"iteration":631,"passed_time":1.10128695,"remaining_time":0.6412556922},
{"learn":[3.632234951],"iteration":632,"passed_time":1.102574589,"remaining_time":0.6392494061},
{"learn":[3.631630987],"iteration":633,"passed_time":1.103711313,"remaining_time":0.6371582661},
{"learn":[3.630301009],"iteration":634,"passed_time":1.104780872,"remaining_time":0.6350315251},
{"learn":[3.629077964],"iteration":635,"passed_time":1.105726296,"remaining_time":0.6328370624},
{"learn":[3.628004522],"iteration":636,"passed_time":1.10667651,"remaining_time":0.6306492512},
{"learn":[3.625062876],"iteration":637,"passed_time":1.107826714,"remaining_time":0.6285787938},
{"learn":[3.624917986],"iteration":638,"passed_time":1.10895808,"remaining_time":0.6265005742},
{"learn":[3.622887087],"iteration":639,"passed_time":1.109991025,"remaining_time":0.6243699514},
{"learn":[3.621220865],"iteration":640,"passed_time":1.11105002,"remaining_time":0.6222573435},
{"learn":[3.621143844],"iteration":641,"passed_time":1.112022065,"remaining_time":0.6200995317},
{"learn":[3.620822821],"iteration":642,"passed_time":1.113004676,"remaining_time":0.6179512742},
{"learn":[3.619202826],"iteration":643,"passed_time":1.114423634,"remaining_time":0.6160478474},
{"learn":[3.618204882],"iteration":644,"passed_time":1.115524993,"remaining_time":0.6139711201},
{"learn":[3.614259666],"iteration":645,"passed_time":1.116845929,"remaining_time":0.6120177379},
{"learn":[3.613415661],"iteration":646,"passed_time":1.118066299,"remaining_time":0.6100114431},
{"learn":[3.611096773],"iteration":647,"passed_time":1.119285865,"remaining_time":0.6080071365},
{"learn":[3.610820695],"iteration":648,"passed_time":1.120345454,"remaining_time":0.6059187276},
{"learn":[3.609290065],"iteration":649,"passed_time":1.121378268,"remaining_time":0.6038190676},
{"learn":[3.60897947],"iteration":650,"passed_time":1.122606288,"remaining_time":0.6018273341},
{"learn":[3.606570702],"iteration":651,"passed_time":1.123748514,"remaining_time":0.5997921515},
{"learn":[3.606292637],"iteration":652,"passed_time":1.125208179,"remaining_time":0.5979283894},
{"learn":[3.602753838],"iteration":653,"passed_time":1.126366441,"remaining_time":0.5959064043},
{"learn":[3.599755869],"iteration":654,"passed_time":1.127523233,"remaining_time":0.5938862833},
{"learn":[3.599509575],"iteration":655,"passed_time":1.128787403,"remaining_time":0.5919251016},
{"learn":[3.595337722],"iteration":656,"passed_time":1.130172859,"remaining_time":0.5900293618},
{"learn":[3.595168561],"iteration":657,"passed_time":1.131477422,"remaining_time":0.588093128},
{"learn":[3.59290559],"iteration":658,"passed_time":1.132621357,"remaining_time":0.5860756948},
{"learn":[3.592015928],"iteration":659,"passed_time":1.133564708,"remaining_time":0.5839575768},
{"learn":[3.590680403],"iteration":660,"passed_time":1.134680744,"remaining_time":0.5819315767},
{"learn":[3.590361532],"iteration":661,"passed_time":1.135629246,"remaining_time":0.5798227871},
{"learn":[3.589069739],"iteration":662,"passed_time":1.136528798,"remaining_time":0.5776926169},
{"learn":[3.585010186],"iteration":663,"passed_time":1.137439867,"remaining_time":0.5755719807},
{"learn":[3.582997552],"iteration":664,"passed_time":1.138386204,"remaining_time":0.5734727494},
{"learn":[3.582119256],"iteration":665,"passed_time":1.139438692,"remaining_time":0.5714302151},
{"learn":[3.579019356],"iteration":666,"passed_time":1.140430546,"remaining_time":0.5693603777},
{"learn":[3.57719559],"iteration":667,"passed_time":1.141702309,"remaining_time":0.567432884},
{"learn":[3.574050046],"iteration":668,"passed_time":1.142682779,"remaining_time":0.5653632282},
{"learn":[3.572204518],"iteration":669,"passed_time":1.143987481,"remaining_time":0.5634565204},
{"learn":[3.569508025],"iteration":670,"passed_time":1.144974129,"remaining_time":0.5613956606},
{"learn":[3.566268704],"iteration":671,"passed_time":1.146045636,"remaining_time":0.5593794176},
{"learn":[3.562564052],"iteration":672,"passed_time":1.147297854,"remaining_time":0.5574537863},
{"learn":[3.561173586],"iteration":673,"passed_time":1.148527545,"remaining_time":0.5555192577},
{"learn":[3.559551904],"iteration":674,"passed_time":1.149629817,"remaining_time":0.5535254674},
{"learn":[3.558593054],"iteration":675,"passed_time":1.15061401,"remaining_time":0.5514777207},
{"learn":[3.555647008],"iteration":676,"passed_time":1.151742424,"remaining_time":0.5495019245},
{"learn":[3.553100059],"iteration":677,"passed_time":1.152925895,"remaining_time":0.547554776},
{"learn":[3.55085578],"iteration":678,"passed_time":1.153888858,"remaining_time":0.5455056309},
{"learn":[3.550737965],"iteration":679,"passed_time":1.155050083,"remaining_time":0.5435529804},
{"learn":[3.549408772],"iteration":680,"passed_time":1.156359291,"remaining_time":0.5416719734},
{"learn":[3.547390589],"iteration":681,"passed_time":1.157537605,"remaining_time":0.5397316107},
{"learn":[3.54723575],"iteration":682,"passed_time":1.158546139,"remaining_time":0.5377146795},
{"learn":[3.543988891],"iteration":683,"passed_time":1.159574793,"remaining_time":0.535709992},
{"learn":[3.543868508],"iteration":684,"passed_time":1.160464176,"remaining_time":0.5336441101},
{"learn":[3.542752124],"iteration":685,"passed_time":1.161514438,"remaining_time":0.5316552968},
{"learn":[3.541334315],"iteration":686,"passed_time":1.162838926,"remaining_time":0.5297941542},
{"learn":[3.540208266],"iteration":687,"passed_time":1.163804682,"remaining_time":0.5277718909},
{"learn":[3.537730983],"iteration":688,"passed_time":1.164775318,"remaining_time":0.5257548969},
{"learn":[3.53419867],"iteration":689,"passed_time":1.165871419,"remaining_time":0.5237973043},
{"learn":[3.532628335],"iteration":690,"passed_time":1.167227227,"remaining_time":0.5219583403},
{"learn":[3.532204987],"iteration":691,"passed_time":1.168340293,"remaining_time":0.5200127315},
{"learn":[3.530618147],"iteration":692,"passed_time":1.169502601,"remaining_time":0.51809134},
{"learn":[3.528909306],"iteration":693,"passed_time":1.170577729,"remaining_time":0.516133696},
{"learn":[3.526700678],"iteration":694,"passed_time":1.17151101,"remaining_time":0.5141163424},
{"learn":[3.526439574],"iteration":695,"passed_time":1.172502795,"remaining_time":0.5121276576},
{"learn":[3.525784216],"iteration":696,"passed_time":1.173773511,"remaining_time":0.5102630903},
{"learn":[3.524112693],"iteration":697,"passed_time":1.174714866,"remaining_time":0.5082577212},
{"learn":[3.522813541],"iteration":698,"passed_time":1.175801449,"remaining_time":0.5063179342},
{"learn":[3.519148203],"iteration":699,"passed_time":1.176821156,"remaining_time":0.504351924},
{"learn":[3.517236747],"iteration":700,"passed_time":1.177975623,"remaining_time":0.5024460932},
{"learn":[3.515603888],"iteration":701,"passed_time":1.178984902,"remaining_time":0.5004807705},
{"learn":[3.51263524],"iteration":702,"passed_time":1.179972675,"remaining_time":0.4985090818},
{"learn":[3.51123442],"iteration":703,"passed_time":1.180893756,"remaining_time":0.4965121476},
{"learn":[3.50828027],"iteration":704,"passed_time":1.181881006,"remaining_time":0.494545953},
{"learn":[3.508265537],"iteration":705,"passed_time":1.182474063,"remaining_time":0.4924183774},
{"learn":[3.506774876],"iteration":706,"passed_time":1.183649508,"remaining_time":0.4905365003},
{"learn":[3.50552068],"iteration":707,"passed_time":1.184728148,"remaining_time":0.4886166937},
{"learn":[3.501973993],"iteration":708,"passed_time":1.185693339,"remaining_time":0.4866526963},
{"learn":[3.498880354],"iteration":709,"passed_time":1.186657295,"remaining_time":0.4846910077},
{"learn":[3.497370959],"iteration":710,"passed_time":1.187636286,"remaining_time":0.4827382372},
{"learn":[3.496050455],"iteration":711,"passed_time":1.188646824,"remaining_time":0.4808009626},
{"learn":[3.495630067],"iteration":712,"passed_time":1.189586557,"remaining_time":0.4788377866},
{"learn":[3.49550669],"iteration":713,"passed_time":1.190537826,"remaining_time":0.4768820983},
{"learn":[3.493652375],"iteration":714,"passed_time":1.191490369,"remaining_time":0.4749297275},
{"learn":[3.491915684],"iteration":715,"passed_time":1.192512461,"remaining_time":0.4730077359},
{"learn":[3.490303956],"iteration":716,"passed_time":1.193407731,"remaining_time":0.4710381981},
{"learn":[3.488363853],"iteration":717,"passed_time":1.194460008,"remaining_time":0.469133318},
{"learn":[3.485483936],"iteration":718,"passed_time":1.19548956,"remaining_time":0.467221928},
{"learn":[3.483763466],"iteration":719,"passed_time":1.19645586,"remaining_time":0.4652883899},
{"learn":[3.481642352],"iteration":720,"passed_time":1.197608657,"remaining_time":0.4634297023},
{"learn":[3.479826119],"iteration":721,"passed_time":1.198576414,"remaining_time":0.4615017219},
{"learn":[3.478588728],"iteration":722,"passed_time":1.199476815,"remaining_time":0.4595505918},
{"learn":[3.475390887],"iteration":723,"passed_time":1.200638523,"remaining_time":0.4577019784},
{"learn":[3.472636852],"iteration":724,"passed_time":1.201607076,"remaining_time":0.4557819945},
{"learn":[3.47061883],"iteration":725,"passed_time":1.202701502,"remaining_time":0.453912137},
{"learn":[3.46953149],"iteration":726,"passed_time":1.203859754,"remaining_time":0.4520683809},
{"learn":[3.467217162],"iteration":727,"passed_time":1.204844529,"remaining_time":0.4501616923},
{"learn":[3.465686216],"iteration":728,"passed_time":1.206038738,"remaining_time":0.4483353882},
{"learn":[3.462631216],"iteration":729,"passed_time":1.207020707,"remaining_time":0.4464323165},
{"learn":[3.461451053],"iteration":730,"passed_time":1.208011451,"remaining_time":0.4445349938},
{"learn":[3.458950469],"iteration":731,"passed_time":1.209003956,"remaining_time":0.4426407925},
{"learn":[3.458072145],"iteration":732,"passed_time":1.210006998,"remaining_time":0.4407528901},
{"learn":[3.454364268],"iteration":733,"passed_time":1.211244668,"remaining_time":0.4389524274},
{"learn":[3.453243406],"iteration":734,"passed_time":1.212477268,"remaining_time":0.4371516679},
{"learn":[3.453017963],"iteration":735,"passed_time":1.213648479,"remaining_time":0.4353304328},
{"learn":[3.45201581],"iteration":736,"passed_time":1.214595627,"remaining_time":0.4334310039},
{"learn":[3.449510107],"iteration":737,"passed_time":1.215496158,"remaining_time":0.4315176062},
{"learn":[3.447189189],"iteration":738,"passed_time":1.216476835,"remaining_time":0.4296352555},
{"learn":[3.446423605],"iteration":739,"passed_time":1.217602779,"remaining_time":0.4278063817},
{"learn":[3.445531987],"iteration":740,"passed_time":1.218700812,"remaining_time":0.4259696497},
{"learn":[3.445328199],"iteration":741,"passed_time":1.219656533,"remaining_time":0.4240854251},
{"learn":[3.443327544],"iteration":742,"passed_time":1.220581453,"remaining_time":0.4221930463},
{"learn":[3.441475798],"iteration":743,"passed_time":1.221536471,"remaining_time":0.4203136243},
{"learn":[3.439046501],"iteration":744,"passed_time":1.222446339,"remaining_time":0.4184212302},
{"learn":[3.435899469],"iteration":745,"passed_time":1.223479354,"remaining_time":0.4165733993},
{"learn":[3.433988352],"iteration":746,"passed_time":1.224646379,"remaining_time":0.4147731376},
{"learn":[3.433413263],"iteration":747,"passed_time":1.225664524,"remaining_time":0.4129244119},
{"learn":[3.429944699],"iteration":748,"passed_time":1.226626143,"remaining_time":0.4110589612},
{"learn":[3.429291634],"iteration":749,"passed_time":1.227532978,"remaining_time":0.4091776594},
{"learn":[3.429175603],"iteration":750,"passed_time":1.228486798,"remaining_time":0.4073145308},
{"learn":[3.428780323],"iteration":751,"passed_time":1.229422395,"remaining_time":0.4054478112},
{"learn":[3.423893341],"iteration":752,"passed_time":1.230404244,"remaining_time":0.403598736},
{"learn":[3.421024316],"iteration":753,"passed_time":1.231385381,"remaining_time":0.4017517292},
{"learn":[3.420969872],"iteration":754,"passed_time":1.232305116,"remaining_time":0.3998870905},
{"learn":[3.419544785],"iteration":755,"passed_time":1.233424235,"remaining_time":0.3980893034},
{"learn":[3.417057977],"iteration":756,"passed_time":1.234386357,"remaining_time":0.3962429125},
{"learn":[3.415160245],"iteration":757,"passed_time":1.235318178,"remaining_time":0.3943891809},
{"learn":[3.412854597],"iteration":758,"passed_time":1.236216642,"remaining_time":0.3925272867},
{"learn":[3.410926347],"iteration":759,"passed_time":1.237192243,"remaining_time":0.3906922873},
{"learn":[3.408963843],"iteration":760,"passed_time":1.23821204,"remaining_time":0.3888734264},
{"learn":[3.407629634],"iteration":761,"passed_time":1.23917368,"remaining_time":0.3870384986},
{"learn":[3.404384724],"iteration":762,"passed_time":1.240121951,"remaining_time":0.385201707},
{"learn":[3.403041656],"iteration":763,"passed_time":1.241046709,"remaining_time":0.3833599782},
{"learn":[3.401101731],"iteration":764,"passed_time":1.241946198,"remaining_time":0.3815128844},
{"learn":[3.400890668],"iteration":765,"passed_time":1.242861817,"remaining_time":0.3796731922},
{"learn":[3.399289941],"iteration":766,"passed_time":1.243839869,"remaining_time":0.3778548756},
{"learn":[3.399202366],"iteration":767,"passed_time":1.244879564,"remaining_time":0.3760573681},
{"learn":[3.397447845],"iteration":768,"passed_time":1.246063326,"remaining_time":0.3743051084},
{"learn":[3.394655341],"iteration":769,"passed_time":1.247260387,"remaining_time":0.3725582975},
{"learn":[3.393228229],"iteration":770,"passed_time":1.248341608,"remaining_time":0.3707785061},
{"learn":[3.389691197],"iteration":771,"passed_time":1.249398369,"remaining_time":0.3689933008},
{"learn":[3.389626772],"iteration":772,"passed_time":1.250440045,"remaining_time":0.3672055502},
{"learn":[3.388480222],"iteration":773,"passed_time":1.25170935,"remaining_time":0.3654861926},
{"learn":[3.388215066],"iteration":774,"passed_time":1.252881491,"remaining_time":0.3637397876},
{"learn":[3.386324358],"iteration":775,"passed_time":1.253920173,"remaining_time":0.3619563387},
{"learn":[3.383913061],"iteration":776,"passed_time":1.255015543,"remaining_time":0.360191076},
{"learn":[3.382839768],"iteration":777,"passed_time":1.256089253,"remaining_time":0.358421355},
{"learn":[3.381961844],"iteration":778,"passed_time":1.25710871,"remaining_time":0.3566380295},
{"learn":[3.381521703],"iteration":779,"passed_time":1.258113347,"remaining_time":0.3548524825},
{"learn":[3.380918963],"iteration":780,"passed_time":1.259404021,"remaining_time":0.353149143},
{"learn":[3.377139006],"iteration":781,"passed_time":1.260542457,"remaining_time":0.351404419},
{"learn":[3.376004372],"iteration":782,"passed_time":1.26181005,"remaining_time":0.3496970382},
{"learn":[3.373826468],"iteration":783,"passed_time":1.262932581,"remaining_time":0.347950813},
{"learn":[3.373546786],"iteration":784,"passed_time":1.263966712,"remaining_time":0.3461819656},
{"learn":[3.372109181],"iteration":785,"passed_time":1.265111172,"remaining_time":0.3444450264},
{"learn":[3.370764924],"iteration":786,"passed_time":1.266349901,"remaining_time":0.3427351068},
{"learn":[3.367833107],"iteration":787,"passed_time":1.267423437,"remaining_time":0.34098194},
{"learn":[3.36450404],"iteration":788,"passed_time":1.268605573,"remaining_time":0.3392595385},
{"learn":[3.361794558],"iteration":789,"passed_time":1.269772147,"remaining_time":0.3375343682},
{"learn":[3.356880529],"iteration":790,"passed_time":1.270861427,"remaining_time":0.3357901875},
{"learn":[3.353843509],"iteration":791,"passed_time":1.272023726,"remaining_time":0.3340668372},
{"learn":[3.353640253],"iteration":792,"passed_time":1.273037322,"remaining_time":0.3323060853},
{"learn":[3.353055088],"iteration":793,"passed_time":1.274024739,"remaining_time":0.3305404235},
{"learn":[3.351415617],"iteration":794,"passed_time":1.275065669,"remaining_time":0.3287905185},
{"learn":[3.349169061],"iteration":795,"passed_time":1.276331099,"remaining_time":0.3270999298},
{"learn":[3.346211014],"iteration":796,"passed_time":1.277336796,"remaining_time":0.3253442528},
{"learn":[3.344560452],"iteration":797,"passed_time":1.27832712,"remaining_time":0.3235865642},
{"learn":[3.344445461],"iteration":798,"passed_time":1.279277643,"remaining_time":0.3218207837},
{"learn":[3.342608898],"iteration":799,"passed_time":1.280671616,"remaining_time":0.320167904},
{"learn":[3.339572899],"iteration":800,"passed_time":1.281760528,"remaining_time":0.3184398815},
{"learn":[3.339309302],"iteration":801,"passed_time":1.282790288,"remaining_time":0.3166988491},
{"learn":[3.33698088],"iteration":802,"passed_time":1.283942974,"remaining_time":0.3149897458},
{"learn":[3.334746342],"iteration":803,"passed_time":1.285035146,"remaining_time":0.3132672744},
{"learn":[3.332048511],"iteration":804,"passed_time":1.2861242,"remaining_time":0.3115456137},
{"learn":[3.331932544],"iteration":805,"passed_time":1.287042091,"remaining_time":0.3097843246},
{"learn":[3.330541133],"iteration":806,"passed_time":1.287972899,"remaining_time":0.3080282149},
{"learn":[3.329124989],"iteration":807,"passed_time":1.288912074,"remaining_time":0.3062761363},
{"learn":[3.32583918],"iteration":808,"passed_time":1.289820935,"remaining_time":0.3045189106},
{"learn":[3.325287299],"iteration":809,"passed_time":1.29085758,"remaining_time":0.3027937533},
{"learn":[3.322745162],"iteration":810,"passed_time":1.29181841,"remaining_time":0.3010526256},
{"learn":[3.319733662],"iteration":811,"passed_time":1.292746254,"remaining_time":0.299305783},
{"learn":[3.318080007],"iteration":812,"passed_time":1.293861581,"remaining_time":0.2976040783},
{"learn":[3.317179538],"iteration":813,"passed_time":1.295046737,"remaining_time":0.2959197704},
{"learn":[3.315685949],"iteration":814,"passed_time":1.296018429,"remaining_time":0.2941882323},
{"learn":[3.314944576],"iteration":815,"passed_time":1.29720634,"remaining_time":0.292507312},
{"learn":[3.312369052],"iteration":816,"passed_time":1.298245329,"remaining_time":0.2907942414},
{"learn":[3.312321621],"iteration":817,"passed_time":1.29897262,"remaining_time":0.2890134681},
{"learn":[3.309465776],"iteration":818,"passed_time":1.299963773,"remaining_time":0.2872935812},
{"learn":[3.308307377],"iteration":819,"passed_time":1.300876883,"remaining_time":0.2855583402},
{"learn":[3.308076804],"iteration":820,"passed_time":1.301988819,"remaining_time":0.2838684515},
{"learn":[3.305643326],"iteration":821,"passed_time":1.303093351,"remaining_time":0.2821783655},
{"learn":[3.304154814],"iteration":822,"passed_time":1.304244622,"remaining_time":0.2804997547},
{"learn":[3.303076321],"iteration":823,"passed_time":1.305822048,"remaining_time":0.2789134472},
{"learn":[3.301746372],"iteration":824,"passed_time":1.306800232,"remaining_time":0.2772000492},
{"learn":[3.301345455],"iteration":825,"passed_time":1.307897525,"remaining_time":0.2755135223},
{"learn":[3.299181039],"iteration":826,"passed_time":1.309013956,"remaining_time":0.2738324237},
{"learn":[3.297989357],"iteration":827,"passed_time":1.310049498,"remaining_time":0.272135886},
{"learn":[3.294775182],"iteration":828,"passed_time":1.311287683,"remaining_time":0.2704827427},
{"learn":[3.293840636],"iteration":829,"passed_time":1.312361504,"remaining_time":0.2687969345},
{"learn":[3.289279397],"iteration":830,"passed_time":1.313374506,"remaining_time":0.2671002305},
{"learn":[3.286204979],"iteration":831,"passed_time":1.314567905,"remaining_time":0.2654415963},
{"learn":[3.284833593],"iteration":832,"passed_time":1.315594573,"remaining_time":0.2637506527},
{"learn":[3.283519914],"iteration":833,"passed_time":1.316635121,"remaining_time":0.2620640649},
{"learn":[3.282853026],"iteration":834,"passed_time":1.317785616,"remaining_time":0.2604007504},
{"learn":[3.281944673],"iteration":835,"passed_time":1.318873399,"remaining_time":0.2587263607},
{"learn":[3.279764865],"iteration":836,"passed_time":1.319895648,"remaining_time":0.2570406102},
{"learn":[3.277468839],"iteration":837,"passed_time":1.321161551,"remaining_time":0.2554035456},
{"learn":[3.277124974],"iteration":838,"passed_time":1.322099108,"remaining_time":0.2537043581},
{"learn":[3.275636037],"iteration":839,"passed_time":1.32303431,"remaining_time":0.2520065352},
{"learn":[3.274413635],"iteration":840,"passed_time":1.324208087,"remaining_time":0.2503556312},
{"learn":[3.272636087],"iteration":841,"passed_time":1.325222125,"remaining_time":0.2486758857},
{"learn":[3.269644466],"iteration":842,"passed_time":1.326168653,"remaining_time":0.2469851466},
{"learn":[3.26852083],"iteration":843,"passed_time":1.327129588,"remaining_time":0.2452988338},
{"learn":[3.267820927],"iteration":844,"passed_time":1.328232095,"remaining_time":0.2436402068},
{"learn":[3.267331099],"iteration":845,"passed_time":1.329413246,"remaining_time":0.2419972103},
{"learn":[3.267231014],"iteration":846,"passed_time":1.330516883,"remaining_time":0.2403413024},
{"learn":[3.267158695],"iteration":847,"passed_time":1.331753537,"remaining_time":0.2387105397},
{"learn":[3.264718705],"iteration":848,"passed_time":1.332878781,"remaining_time":0.2370608903},
{"learn":[3.261678512],"iteration":849,"passed_time":1.333916754,"remaining_time":0.2353970743},
{"learn":[3.261368381],"iteration":850,"passed_time":1.334918071,"remaining_time":0.2337283108},
{"learn":[3.260128799],"iteration":851,"passed_time":1.335867121,"remaining_time":0.2320520351},
{"learn":[3.258972952],"iteration":852,"passed_time":1.336990536,"remaining_time":0.2304075133},
{"learn":[3.258724846],"iteration":853,"passed_time":1.337944285,"remaining_time":0.2287352056},
{"learn":[3.25686724],"iteration":854,"passed_time":1.339132906,"remaining_time":0.2271044109},
{"learn":[3.255750259],"iteration":855,"passed_time":1.340055666,"remaining_time":0.2254299252},
{"learn":[3.254915866],"iteration":856,"passed_time":1.340955256,"remaining_time":0.2237533274},
{"learn":[3.254348625],"iteration":857,"passed_time":1.341889772,"remaining_time":0.2220843213},
{"learn":[3.253408514],"iteration":858,"passed_time":1.34280875,"remaining_time":0.2204144747},
{"learn":[3.253291714],"iteration":859,"passed_time":1.343961261,"remaining_time":0.2187843913},
{"learn":[3.250186342],"iteration":860,"passed_time":1.34522792,"remaining_time":0.2171738455},
{"learn":[3.249141318],"iteration":861,"passed_time":1.346173142,"remaining_time":0.2155126376},
{"learn":[3.246300388],"iteration":862,"passed_time":1.347175031,"remaining_time":0.2138620848},
{"learn":[3.245205135],"iteration":863,"passed_time":1.34831165,"remaining_time":0.2122342411},
{"learn":[3.244403535],"iteration":864,"passed_time":1.34946724,"remaining_time":0.2106104942},
{"learn":[3.244211781],"iteration":865,"passed_time":1.350478507,"remaining_time":0.2089654964},
{"learn":[3.242286347],"iteration":866,"passed_time":1.351384059,"remaining_time":0.2073057438},
{"learn":[3.239606746],"iteration":867,"passed_time":1.352342377,"remaining_time":0.2056557532},
{"learn":[3.236773361],"iteration":868,"passed_time":1.353244833,"remaining_time":0.2039989333},
{"learn":[3.234552446],"iteration":869,"passed_time":1.354359925,"remaining_time":0.202375621},
{"learn":[3.233724647],"iteration":870,"passed_time":1.355406333,"remaining_time":0.200743303},
{"learn":[3.230851485],"iteration":871,"passed_time":1.356344932,"remaining_time":0.1990965038},
{"learn":[3.227728941],"iteration":872,"passed_time":1.357285597,"remaining_time":0.1974516275},
{"learn":[3.225787575],"iteration":873,"passed_time":1.358390917,"remaining_time":0.1958321002},
{"learn":[3.222797487],"iteration":874,"passed_time":1.359347846,"remaining_time":0.1941925494},
{"learn":[3.22137014],"iteration":875,"passed_time":1.360302178,"remaining_time":0.1925541896},
{"learn":[3.219701963],"iteration":876,"passed_time":1.36127989,"remaining_time":0.1909206687},
{"learn":[3.21783327],"iteration":877,"passed_time":1.362265841,"remaining_time":0.1892897865},
{"learn":[3.217713355],"iteration":878,"passed_time":1.363346711,"remaining_time":0.187673438},
{"learn":[3.217666091],"iteration":879,"passed_time":1.364460179,"remaining_time":0.1860627517},
{"learn":[3.214962005],"iteration":880,"passed_time":1.365553493,"remaining_time":0.1844504718},
{"learn":[3.214081828],"iteration":881,"passed_time":1.366584055,"remaining_time":0.1828309733},
{"learn":[3.213358337],"iteration":882,"passed_time":1.367602779,"remaining_time":0.1812112403},
{"learn":[3.210850401],"iteration":883,"passed_time":1.368558126,"remaining_time":0.1795845504},
{"learn":[3.207810328],"iteration":884,"passed_time":1.369555453,"remaining_time":0.1779648328},
{"learn":[3.204935073],"iteration":885,"passed_time":1.370572486,"remaining_time":0.1763490558},
{"learn":[3.20280198],"iteration":886,"passed_time":1.371466648,"remaining_time":0.1747189755},
{"learn":[3.200663495],"iteration":887,"passed_time":1.374778901,"remaining_time":0.173395537},
{"learn":[3.197301669],"iteration":888,"passed_time":1.375950713,"remaining_time":0.1718003702},
{"learn":[3.195666943],"iteration":889,"passed_time":1.378568852,"remaining_time":0.1703849143},
{"learn":[3.193886506],"iteration":890,"passed_time":1.37966631,"remaining_time":0.168780727},
{"learn":[3.190601248],"iteration":891,"passed_time":1.380773917,"remaining_time":0.1671789047},
{"learn":[3.188983797],"iteration":892,"passed_time":1.381996297,"remaining_time":0.1655919415},
{"learn":[3.187365749],"iteration":893,"passed_time":1.382969809,"remaining_time":0.1639762861},
{"learn":[3.186160771],"iteration":894,"passed_time":1.38388723,"remaining_time":0.1623554851},
{"learn":[3.185358981],"iteration":895,"passed_time":1.38485333,"remaining_time":0.1607419044},
{"learn":[3.183832164],"iteration":896,"passed_time":1.385814296,"remaining_time":0.1591291778},
{"learn":[3.183106966],"iteration":897,"passed_time":1.386820787,"remaining_time":0.1575230738},
{"learn":[3.182838152],"iteration":898,"passed_time":1.38804541,"remaining_time":0.1559428102},
{"learn":[3.180835453],"iteration":899,"passed_time":1.389517954,"remaining_time":0.1543908838},
{"learn":[3.179957348],"iteration":900,"passed_time":1.390832094,"remaining_time":0.1528217284},
{"learn":[3.179752966],"iteration":901,"passed_time":1.391790434,"remaining_time":0.1512144817},
{"learn":[3.178851983],"iteration":902,"passed_time":1.393041159,"remaining_time":0.1496400802},
{"learn":[3.176748586],"iteration":903,"passed_time":1.393990304,"remaining_time":0.1480343686},
{"learn":[3.172960988],"iteration":904,"passed_time":1.395265171,"remaining_time":0.1464642998},
{"learn":[3.172794225],"iteration":905,"passed_time":1.39620806,"remaining_time":0.1448604388},
{"learn":[3.169996507],"iteration":906,"passed_time":1.397281778,"remaining_time":0.1432714503},
{"learn":[3.16813015],"iteration":907,"passed_time":1.398241296,"remaining_time":0.1416720255},
{"learn":[3.166920871],"iteration":908,"passed_time":1.399136055,"remaining_time":0.1400675258},
{"learn":[3.16531606],"iteration":909,"passed_time":1.400043102,"remaining_time":0.1384658013},
{"learn":[3.162035247],"iteration":910,"passed_time":1.400994101,"remaining_time":0.1368698957},
{"learn":[3.16189467],"iteration":911,"passed_time":1.401932395,"remaining_time":0.1352741785},
{"learn":[3.161008416],"iteration":912,"passed_time":1.402985628,"remaining_time":0.1336908539},
{"learn":[3.160560787],"iteration":913,"passed_time":1.404044987,"remaining_time":0.1321092658},
{"learn":[3.160416261],"iteration":914,"passed_time":1.404993606,"remaining_time":0.1305185317},
{"learn":[3.15844291],"iteration":915,"passed_time":1.405900134,"remaining_time":0.1289253398},
{"learn":[3.155040501],"iteration":916,"passed_time":1.406904538,"remaining_time":0.1273425045},
{"learn":[3.154937548],"iteration":917,"passed_time":1.407876247,"remaining_time":0.125758009},
{"learn":[3.153721161],"iteration":918,"passed_time":1.408874964,"remaining_time":0.1241772275},
{"learn":[3.153170511],"iteration":919,"passed_time":1.409848202,"remaining_time":0.1225954958},
{"learn":[3.153113601],"iteration":920,"passed_time":1.410723458,"remaining_time":0.121006681},
{"learn":[3.150607379],"iteration":921,"passed_time":1.411725418,"remaining_time":0.119430133},
{"learn":[3.148408359],"iteration":922,"passed_time":1.412655595,"remaining_time":0.1178488416},
{"learn":[3.147495728],"iteration":923,"passed_time":1.41353883,"remaining_time":0.1162650986},
{"learn":[3.146946235],"iteration":924,"passed_time":1.414460782,"remaining_time":0.1146860093},
{"learn":[3.14472738],"iteration":925,"passed_time":1.415417383,"remaining_time":0.1131111083},
{"learn":[3.144469477],"iteration":926,"passed_time":1.41655982,"remaining_time":0.1115521757},
{"learn":[3.142975516],"iteration":927,"passed_time":1.417512288,"remaining_time":0.1099794017},
{"learn":[3.14079113],"iteration":928,"passed_time":1.418439103,"remaining_time":0.1084060025},
{"learn":[3.138173032],"iteration":929,"passed_time":1.419340223,"remaining_time":0.1068320598},
{"learn":[3.136352813],"iteration":930,"passed_time":1.42035312,"remaining_time":0.1052678467},
{"learn":[3.133735004],"iteration":931,"passed_time":1.421282458,"remaining_time":0.1036987201},
{"learn":[3.1319496],"iteration":932,"passed_time":1.422373021,"remaining_time":0.1021425428},
{"learn":[3.129865343],"iteration":933,"passed_time":1.423467334,"remaining_time":0.1005876275},
{"learn":[3.129830206],"iteration":934,"passed_time":1.424223364,"remaining_time":0.09901018035},
{"learn":[3.126676562],"iteration":935,"passed_time":1.425161281,"remaining_time":0.0974469252},
{"learn":[3.12645665],"iteration":936,"passed_time":1.426053044,"remaining_time":0.09588190158},
{"learn":[3.126378007],"iteration":937,"passed_time":1.426984712,"remaining_time":0.09432095114},
{"learn":[3.124621914],"iteration":938,"passed_time":1.427963722,"remaining_time":0.09276441644},
{"learn":[3.123379018],"iteration":939,"passed_time":1.428841708,"remaining_time":0.09120266222},
{"learn":[3.123332451],"iteration":940,"passed_time":1.429983921,"remaining_time":0.08965892813},
{"learn":[3.122432444],"iteration":941,"passed_time":1.43117831,"remaining_time":0.088119259},
{"learn":[3.121889006],"iteration":942,"passed_time":1.432275428,"remaining_time":0.08657444263},
{"learn":[3.121070914],"iteration":943,"passed_time":1.433323381,"remaining_time":0.08502765818},
{"learn":[3.118444705],"iteration":944,"passed_time":1.434596313,"remaining_time":0.0834950235},
{"learn":[3.116820458],"iteration":945,"passed_time":1.43596746,"remaining_time":0.08196854422},
{"learn":[3.114971041],"iteration":946,"passed_time":1.437372483,"remaining_time":0.0804442889},
{"learn":[3.114685138],"iteration":947,"passed_time":1.438574577,"remaining_time":0.078909154},
{"learn":[3.113399363],"iteration":948,"passed_time":1.439833737,"remaining_time":0.07737778774},
{"learn":[3.110575399],"iteration":949,"passed_time":1.441058847,"remaining_time":0.07584520245},
{"learn":[3.110466553],"iteration":950,"passed_time":1.44203683,"remaining_time":0.07430053066},
{"learn":[3.108691641],"iteration":951,"passed_time":1.443170069,"remaining_time":0.07276487745},
{"learn":[3.107898017],"iteration":952,"passed_time":1.444413844,"remaining_time":0.07123552013},
{"learn":[3.105551729],"iteration":953,"passed_time":1.445575934,"remaining_time":0.06970282283},
{"learn":[3.104824945],"iteration":954,"passed_time":1.446687307,"remaining_time":0.06816851184},
{"learn":[3.103186704],"iteration":955,"passed_time":1.448052262,"remaining_time":0.06664675684},
{"learn":[3.102330655],"iteration":956,"passed_time":1.449453933,"remaining_time":0.06512697922},
{"learn":[3.102291298],"iteration":957,"passed_time":1.450739413,"remaining_time":0.0636023542},
{"learn":[3.100363529],"iteration":958,"passed_time":1.452065342,"remaining_time":0.06207995726},
{"learn":[3.097871596],"iteration":959,"passed_time":1.453417233,"remaining_time":0.06055905137},
{"learn":[3.097372213],"iteration":960,"passed_time":1.454821359,"remaining_time":0.05904061707},
{"learn":[3.095981813],"iteration":961,"passed_time":1.456127132,"remaining_time":0.05751853535},
{"learn":[3.095347452],"iteration":962,"passed_time":1.45725988,"remaining_time":0.055990255},
{"learn":[3.094728409],"iteration":963,"passed_time":1.458648749,"remaining_time":0.05447235994},
{"learn":[3.094118537],"iteration":964,"passed_time":1.459882377,"remaining_time":0.05294910177},
{"learn":[3.093793695],"iteration":965,"passed_time":1.461009567,"remaining_time":0.05142269699},
{"learn":[3.092581602],"iteration":966,"passed_time":1.462394696,"remaining_time":0.04990592034},
{"learn":[3.091694202],"iteration":967,"passed_time":1.463716972,"remaining_time":0.04838733792},
{"learn":[3.090298312],"iteration":968,"passed_time":1.464892064,"remaining_time":0.046864452},
{"learn":[3.090020107],"iteration":969,"passed_time":1.466192585,"remaining_time":0.04534616242},
{"learn":[3.088949869],"iteration":970,"passed_time":1.467552658,"remaining_time":0.04383009998},
{"learn":[3.086700204],"iteration":971,"passed_time":1.468938762,"remaining_time":0.04231510838},
{"learn":[3.086584317],"iteration":972,"passed_time":1.470293547,"remaining_time":0.04079951261},
{"learn":[3.084850742],"iteration":973,"passed_time":1.471659357,"remaining_time":0.03928454137},
{"learn":[3.084239948],"iteration":974,"passed_time":1.472905269,"remaining_time":0.03776680177},
{"learn":[3.082561673],"iteration":975,"passed_time":1.474033258,"remaining_time":0.03624671945},
{"learn":[3.07991814],"iteration":976,"passed_time":1.475023615,"remaining_time":0.03472419974},
{"learn":[3.079350277],"iteration":977,"passed_time":1.475963445,"remaining_time":0.03320163168},
{"learn":[3.077637462],"iteration":978,"passed_time":1.476890407,"remaining_time":0.03167997808},
{"learn":[3.076733301],"iteration":979,"passed_time":1.477825874,"remaining_time":0.03015971171},
{"learn":[3.07594065],"iteration":980,"passed_time":1.47877789,"remaining_time":0.02864095811},
{"learn":[3.072594655],"iteration":981,"passed_time":1.47974753,"remaining_time":0.02712368182},
{"learn":[3.071977674],"iteration":982,"passed_time":1.480629803,"remaining_time":0.02560600879},
{"learn":[3.069532634],"iteration":983,"passed_time":1.481667439,"remaining_time":0.02409215347},
{"learn":[3.068870784],"iteration":984,"passed_time":1.48260393,"remaining_time":0.02257772482},
{"learn":[3.068801463],"iteration":985,"passed_time":1.483447281,"remaining_time":0.02106314598},
{"learn":[3.067433249],"iteration":986,"passed_time":1.484374127,"remaining_time":0.019551027},
{"learn":[3.065611456],"iteration":987,"passed_time":1.485253162,"remaining_time":0.01803951209},
{"learn":[3.063039162],"iteration":988,"passed_time":1.486435745,"remaining_time":0.01653265237},
{"learn":[3.06177873],"iteration":989,"passed_time":1.487402254,"remaining_time":0.01502426519},
{"learn":[3.061689148],"iteration":990,"passed_time":1.48826205,"remaining_time":0.01351600247},
{"learn":[3.058984039],"iteration":991,"passed_time":1.489137603,"remaining_time":0.01200917422},
{"learn":[3.057492984],"iteration":992,"passed_time":1.490021641,"remaining_time":0.01050367723},
{"learn":[3.057290731],"iteration":993,"passed_time":1.490896963,"remaining_time":0.008999378049},
{"learn":[3.056068348],"iteration":994,"passed_time":1.491733685,"remaining_time":0.00749614917},
{"learn":[3.054987307],"iteration":995,"passed_time":1.492711186,"remaining_time":0.00599482404},
{"learn":[3.054200234],"iteration":996,"passed_time":1.493615476,"remaining_time":0.004494329416},
{"learn":[3.052732869],"iteration":997,"passed_time":1.49456656,"remaining_time":0.002995123366},
{"learn":[3.051787862],"iteration":998,"passed_time":1.495530134,"remaining_time":0.001497027161},
{"learn":[3.051366222],"iteration":999,"passed_time":1.496548512,"remaining_time":0}
]}